Workbook
Name \0: #REF!
Name \0: #REF!
Name \c: #REF!
Name \c: #REF!
Name \d: #N/A
Name \l: #N/A
Name \M: #REF!
Name \M: #REF!
Name \n: #N/A
Name \p: #N/A
Name \r: #N/A
Name \s: #REF!
Name \s: #REF!
Name \t: #N/A
Name \w: #N/A
Name \Y: #REF!
Name \Y: #REF!
Name \z: #N/A
Name _1: #REF!
Name _1: #REF!
Name _10: #N/A
Name _11: #N/A
Name _12: #N/A
Name _13: #N/A
Name _14: #N/A
Name _15: #N/A
Name _16: #N/A
Name _17: #N/A
Name _18: #N/A
Name _19: #N/A
Name _1A: #REF!
Name _1A: #REF!
Name _1F: #REF!
Name _1F: #REF!
Name _1NR: #REF!
Name _1NR: #REF!
Name _1S: #REF!
Name _1S: #REF!
Name _2: #REF!
Name _2: #REF!
Name _20: #N/A
Name _21: #N/A
Name _22: #N/A
Name _2A: #REF!
Name _2A: #REF!
Name _2F: #REF!
Name _2F: #REF!
Name _2S: #REF!
Name _2S: #REF!
Name _3: #N/A
Name _3A: #REF!
Name _3A: #REF!
Name _3S: #REF!
Name _3S: #REF!
Name _4: #N/A
Name _4A: #REF!
Name _4A: #REF!
Name _4S: #REF!
Name _4S: #REF!
Name _5: #N/A

Sheet INC
A1: EXCEL MODELING TEST
A2: Income Statement
A3: (INR, Millions)
B4: =C4-1 -> 2021 | C4: =D4-1 -> 2022 | D4: =E4-1 -> 2023 | E4: 2024 | F4: =+E4+1 -> 2025 | G4: =+F4+1 -> 2026 | H4: =+G4+1 -> 2027 | I4: =+H4+1 -> 2028 | J4: =+I4+1 -> 2029
A6: Net Sales | B6: 75.79 | C6: 94.26 | D6: 108.26 | E6: 125.1 | F6: =F29 -> 150.34671 | G6: =G29 -> 182.19197 | H6: =H29 -> 222.60437 | I6: =I29 -> 274.20678 | J6: =J29 -> 340.51333
A8: Cost of Goods Sold | B8: 49.39 | C8: 59.83 | D8: 69.54 | E8: 81.77 | F8: =F31 -> 96.621965 | G8: =G31 -> 115.0411 | H8: =H31 -> 138.64481 | I8: =I31 -> 168.3739 | J8: =J31 -> 206.03515
A10: SG&A | B10: =SUM(B11:B12) -> 22.6 | C10: =SUM(C11:C12) -> 29.3 | D10: =SUM(D11:D12) -> 32.5 | E10: =SUM(E11:E12) -> 37.3 | F10: =SUM(F11:F12) -> 39.79253 | G10: =SUM(G11:G12) -> 44.049221 | H10: =SUM(H11:H12) -> 49.219722 | I10: =SUM(I11:I12) -> 55.555317 | J10: =SUM(J11:J12) -> 63.389497
A11: Fixed SG &A | B11: 14 | C11: 20 | D11: 22 | E11: 25 | F11: =F36 -> 26.261326 | G11: =G36 -> 27.651944 | H11: =H36 -> 29.185328 | I11: =I36 -> 30.876707 | J11: =J36 -> 32.743298
A12: Variable SG&A | B12: 8.6 | C12: 9.3 | D12: 10.5 | E12: 12.3 | F12: =F38 -> 13.531204 | G12: =G38 -> 16.397277 | H12: =H38 -> 20.034394 | I12: =I38 -> 24.67861 | J12: =J38 -> 30.646199
A14: Provision for warranty | E14: 0.2 | F14: =F44 -> 1.5034671 | G14: =G44 -> 1.8219197 | H14: =H44 -> 2.2260437 | I14: =I44 -> 2.7420678 | J14: =J44 -> 3.4051333
A16: Depreciation | B16: 1.71 | C16: 2.18 | D16: 2.81 | E16: 3.54 | F16: =F42 -> 2.751 | G16: =G42 -> 2.71335 | H16: =H42 -> 2.6063475 | I16: =I42 -> 2.0653954 | J16: =J42 -> 2.3555861
A18: Net Interest Expense | B18: 0.27 | C18: 0.45 | D18: 0.32 | E18: 0.81 | F18: =F48 -> 1.4308 | G18: =G48 -> 1.8264 | H18: =H48 -> 1.6464 | I18: =I48 -> 1.1664 | J18: =J48 -> 0.9864
A20: Income Taxes | B20: 0.6405 | C20: 0.861 | D20: 1.228 | E20: 0.688 | F20: =F51 -> 2.4740832 | G20: =G51 -> 5.0219929 | H20: =H51 -> 8.4783149 | I20: =I51 -> 13.29111 | J20: =J51 -> 19.302468
A22: Dividends | B22: 0 | C22: 0 | D22: 0 | E22: 0 | F22: =F54 -> 0.28864304 | G22: =G54 -> 0.58589918 | H22: =H54 -> 0.98913674 | I22: =I54 -> 1.5506295 | J22: =J54 -> 2.2519546
A25: Construct the Income Statement of the company showing Gross Profit, EBITDA, EBIT & Net Profit
B28: =B4 -> 2021 | C28: =+B28+1 -> 2022 | D28: =+C28+1 -> 2023 | E28: =+D28+1 -> 2024 | F28: =+E28+1 -> 2025 | G28: =+F28+1 -> 2026 | H28: =+G28+1 -> 2027 | I28: =+H28+1 -> 2028 | J28: =+I28+1 -> 2029
A29: Net Sales | B29: =B6 -> 75.79 | C29: =C6 -> 94.26 | D29: =D6 -> 108.26 | E29: =E6 -> 125.1 | F29: =E29*(1+F30) -> 150.34671 | G29: =F29*(1+G30) -> 182.19197 | H29: =G29*(1+H30) -> 222.60437 | I29: =H29*(1+I30) -> 274.20678 | J29: =I29*(1+J30) -> 340.51333
A30: Sales Growth (%) | E30: =(E29/B29)^(1/3)-1 -> 0.1818122 | F30: =$E$30+Instructions!$E$5 -> 0.2018122 | G30: =F30+Instructions!$E$6 -> 0.2118122 | H30: =G30+Instructions!$E$6 -> 0.2218122 | I30: =H30+Instructions!$E$6 -> 0.2318122 | J30: =I30+Instructions!$E$6 -> 0.2418122
A31: COGS | B31: =B8 -> 49.39 | C31: =C8 -> 59.83 | D31: =D8 -> 69.54 | E31: =E8 -> 81.77 | F31: =E31*(1+F32) -> 96.621965 | G31: =F31*(1+G32) -> 115.0411 | H31: =G31*(1+H32) -> 138.64481 | I31: =H31*(1+I32) -> 168.3739 | J31: =I31*(1+J32) -> 206.03515
A32: COGS Growth (%) | F32: =F30*Instructions!$E$9 -> 0.18163098 | G32: =G30*Instructions!$E$9 -> 0.19063098 | H32: =H30*Instructions!$E$11 -> 0.20517628 | I32: =I30*Instructions!$E$11 -> 0.21442628 | J32: =J30*Instructions!$E$11 -> 0.22367628
A33: Gross Profit | B33: =B29-B31 -> 26.4 | C33: =C29-C31 -> 34.43 | D33: =D29-D31 -> 38.72 | E33: =E29-E31 -> 43.33 | F33: =F29-F31 -> 53.724741 | G33: =G29-G31 -> 67.150867 | H33: =H29-H31 -> 83.959563 | I33: =I29-I31 -> 105.83288 | J33: =J29-J31 -> 134.47818
A35: SG&A | B35: =B10 -> 22.6 | C35: =C10 -> 29.3 | D35: =D10 -> 32.5 | E35: =E10 -> 37.3 | F35: =F10 -> 39.79253 | G35: =G10 -> 44.049221 | H35: =H10 -> 49.219722 | I35: =I10 -> 55.555317 | J35: =J10 -> 63.389497
A36: Fixed SG &A | B36: =B11 -> 14 | C36: =C11 -> 20 | D36: =D11 -> 22 | E36: =E11 -> 25 | F36: =E36*(1+F37) -> 26.261326 | G36: =F36*(1+G37) -> 27.651944 | H36: =G36*(1+H37) -> 29.185328 | I36: =H36*(1+I37) -> 30.876707 | J36: =I36*(1+J37) -> 32.743298
A37: Fixed SG&A Growth (%) | F37: =F30*Instructions!$E$15 -> 0.050453049 | G37: =G30*Instructions!$E$15 -> 0.052953049 | H37: =H30*Instructions!$E$15 -> 0.055453049 | I37: =I30*Instructions!$E$15 -> 0.057953049 | J37: =J30*Instructions!$E$15 -> 0.060453049
A38: Variable SG&A | B38: =B12 -> 8.6 | C38: =C12 -> 9.3 | D38: =D12 -> 10.5 | E38: =E12 -> 12.3 | F38: =F39*F29 -> 13.531204 | G38: =G39*G29 -> 16.397277 | H38: =H39*H29 -> 20.034394 | I38: =I39*I29 -> 24.67861 | J38: =J39*J29 -> 30.646199
A39: Variable( as % of sales) | F39: =Instructions!$E$18 -> 0.09 | G39: =Instructions!$E$18 -> 0.09 | H39: =Instructions!$E$18 -> 0.09 | I39: =Instructions!$E$18 -> 0.09 | J39: =Instructions!$E$18 -> 0.09
A40: EBITDA | B40: =B33-B35 -> 3.8 | C40: =C33-C35 -> 5.13 | D40: =D33-D35 -> 6.22 | E40: =E33-E35 -> 6.03 | F40: =F33-F35 -> 13.932211 | G40: =G33-G35 -> 23.101646 | H40: =H33-H35 -> 34.739841 | I40: =I33-I35 -> 50.277563 | J40: =J33-J35 -> 71.088679
A42: Depreciation | B42: =B16 -> 1.71 | C42: =C16 -> 2.18 | D42: =D16 -> 2.81 | E42: =E16 -> 3.54 | F42: =BS!E12*INC!F43 -> 2.751 | G42: =BS!F12*INC!G43 -> 2.71335 | H42: =BS!G12*INC!H43 -> 2.6063475 | I42: =BS!H12*INC!I43 -> 2.0653954 | J42: =BS!I12*INC!J43 -> 2.3555861
A43: Depreciation (%) | F43: =Instructions!$E$20 -> 0.15 | G43: =Instructions!$E$20 -> 0.15 | H43: =Instructions!$E$20 -> 0.15 | I43: =Instructions!$E$20 -> 0.15 | J43: =Instructions!$E$20 -> 0.15
A44: Provision for Warranty | B44: 0 | C44: 0 | D44: 0 | E44: =E14 -> 0.2 | F44: =F29*F45 -> 1.5034671 | G44: =G29*G45 -> 1.8219197 | H44: =H29*H45 -> 2.2260437 | I44: =I29*I45 -> 2.7420678 | J44: =J29*J45 -> 3.4051333
A45: Provision (%) | F45: =Instructions!$E$22 -> 0.01 | G45: =Instructions!$E$22 -> 0.01 | H45: =Instructions!$E$22 -> 0.01 | I45: =Instructions!$E$22 -> 0.01 | J45: =Instructions!$E$22 -> 0.01
A46: EBIT | B46: =B40-B42-B44 -> 2.09 | C46: =C40-C42-C44 -> 2.95 | D46: =D40-D42-D44 -> 3.41 | E46: =E40-E42-E44 -> 2.29 | F46: =F40-F42-F44 -> 9.677744 | G46: =G40-G42-G44 -> 18.566376 | H46: =H40-H42-H44 -> 29.90745 | I46: =I40-I42-I44 -> 45.4701 | J46: =J40-J42-J44 -> 65.327959
A48: Interest | B48: =B18 -> 0.27 | C48: =C18 -> 0.45 | D48: =D18 -> 0.32 | E48: =E18 -> 0.81 | F48: =IF(E46/E48<6,Instructions!$E$38,Instructions!$E$35)*(BS!E22+BS!E23) -> 1.4308 | G48: =IF(F46/F48<6,Instructions!$E$38,Instructions!$E$35)*(BS!F22+BS!F23) -> 1.8264 | H48: =IF(G46/G48<6,Instructions!$E$38,Instructions!$E$35)*(BS!G22+BS!G23) -> 1.6464 | I48: =IF(H46/H48<6,Instructions!$E$38,Instructions!$E$35)*(BS!H22+BS!H23) -> 1.1664 | J48: =IF(I46/I48<6,Instructions!$E$38,Instructions!$E$35)*(BS!I22+BS!I23) -> 0.9864
A49: PBT | B49: =B46-B48 -> 1.82 | C49: =C46-C48 -> 2.5 | D49: =D46-D48 -> 3.09 | E49: =E46-E48 -> 1.48 | F49: =F46-F48 -> 8.246944 | G49: =G46-G48 -> 16.739976 | H49: =H46-H48 -> 28.26105 | I49: =I46-I48 -> 44.3037 | J49: =J46-J48 -> 64.341559
A51: Tax | B51: =B20 -> 0.6405 | C51: =C20 -> 0.861 | D51: =D20 -> 1.228 | E51: =E20 -> 0.688 | F51: =F49*Instructions!$E$29 -> 2.4740832 | G51: =G49*Instructions!$E$29 -> 5.0219929 | H51: =H49*Instructions!$E$29 -> 8.4783149 | I51: =I49*Instructions!$E$29 -> 13.29111 | J51: =J49*Instructions!$E$29 -> 19.302468
A53: Net Profit | B53: =B49-B51 -> 1.1795 | C53: =C49-C51 -> 1.639 | D53: =D49-D51 -> 1.862 | E53: =E49-E51 -> 0.792 | F53: =F49-F51 -> 5.7728608 | G53: =G49-G51 -> 11.717984 | H53: =H49-H51 -> 19.782735 | I53: =I49-I51 -> 31.01259 | J53: =J49-J51 -> 45.039091
A54: Dividend Payout | F54: =F53*Instructions!$K$11 -> 0.28864304 | G54: =G53*Instructions!$K$11 -> 0.58589918 | H54: =H53*Instructions!$K$11 -> 0.98913674 | I54: =I53*Instructions!$K$11 -> 1.5506295 | J54: =J53*Instructions!$K$11 -> 2.2519546

Sheet BS
A1: =INC!A1 -> EXCEL MODELING TEST
A2: Balance Sheet
A3: (INR, Millions)
D4: =+INC!D4 -> 2023 | E4: =+INC!E4 -> 2024 | F4: =+INC!F4 -> 2025 | G4: =+INC!G4 -> 2026 | H4: =+INC!H4 -> 2027 | I4: =+INC!I4 -> 2028 | J4: =+INC!J4 -> 2029
A6: Cash and Equivalents | D6: 0.43 | E6: 1.03 | F6: =CFS!F42 -> 6.0720619 | G6: =CFS!G42 -> 7.6618606 | H6: =CFS!H42 -> 17.768216 | I6: =CFS!I42 -> 30.328271 | J6: =CFS!J42 -> 51.475317
A7: Accounts Receivables | D7: 5.48 | E7: 5.82 | F7: =F37 -> 6.994547 | G7: =G37 -> 8.4760773 | H7: =H37 -> 10.356175 | I7: =I37 -> 12.756862 | J7: =J37 -> 15.841627
A8: Inventory | D8: 28.54 | E8: 31.44 | F8: =F38 -> 37.784975 | G8: =G38 -> 45.788294 | H8: =H38 -> 55.944696 | I8: =I38 -> 68.913359 | J8: =J38 -> 85.57745
A9: Other Current Assets | D9: 4.46 | E9: 5.69 | F9: =F39 -> 6.8383114 | G9: =G39 -> 8.2867492 | H9: =H39 -> 10.124851 | I9: =I39 -> 12.471915 | J9: =J39 -> 15.487776
A10: Current Assets | D10: =+SUM(D6:D9) -> 38.91 | E10: =+SUM(E6:E9) -> 43.98 | F10: =+SUM(F6:F9) -> 57.689896 | G10: =+SUM(G6:G9) -> 70.212981 | H10: =+SUM(H6:H9) -> 94.193938 | I10: =+SUM(I6:I9) -> 124.47041 | J10: =+SUM(J6:J9) -> 168.38217
A12: Net Property, Plant and Equipment (Net Block) | D12: 17.1 | E12: 18.34 | F12: =F40 -> 18.089 | G12: =G40 -> 17.37565 | H12: =H40 -> 13.769303 | I12: =I40 -> 15.703907 | J12: =J40 -> 18.848321
A13: Other Long-term Assets (Land) | D13: 3.59 | E13: 2.51 | F13: =E13 -> 2.51 | G13: =F13 -> 2.51 | H13: =G13 -> 2.51 | I13: =H13 -> 2.51 | J13: =I13 -> 2.51
A14: Investment In Subsidiary | D14: 0 | E14: 0 | F14: =F41 -> 5 | G14: =G41 -> 5 | H14: =H41 -> 5 | I14: =I41 -> 3 | J14: =J41 -> 0
A15: Total Assets | D15: =+SUM(D10,D12:D14) -> 59.6 | E15: =+SUM(E10,E12:E14) -> 64.83 | F15: =F10+F12+F13+F14 -> 83.288896 | G15: =G10+G12+G13+G14 -> 95.098631 | H15: =H10+H12+H13+H14 -> 115.47324 | I15: =I10+I12+I13+I14 -> 145.68431 | J15: =J10+J12+J13+J14 -> 189.74049
A18: Accounts Payable | D18: 6.67 | E18: 4.79 | F18: =F42 -> 5.7566804 | G18: =G42 -> 6.9760155 | H18: =H42 -> 8.5233809 | I18: =I42 -> 10.499205 | J18: =J42 -> 13.03804
A19: Other Current Liabilities | D19: 4.12 | E19: 2.5 | F19: =F43 -> 3.0045305 | G19: =G43 -> 3.6409267 | H19: =H43 -> 4.4485286 | I19: =I43 -> 5.4797518 | J19: =J43 -> 6.8048227
A20: Current Liabilities | D20: =SUM(D18:D19) -> 10.79 | E20: =SUM(E18:E19) -> 7.29 | F20: =SUM(F18:F19) -> 8.7612109 | G20: =SUM(G18:G19) -> 10.616942 | H20: =SUM(H18:H19) -> 12.97191 | I20: =SUM(I18:I19) -> 15.978956 | J20: =SUM(J18:J19) -> 19.842863
A22: Debt | D22: =(0.11+12.53)-5 -> 7.64 | E22: =(19.71+0.73)-5 -> 15.44 | F22: =F45 -> 25.44 | G22: =G45 -> 22.44 | H22: =H45 -> 19.44 | I22: =I45 -> 16.44 | J22: =J45 -> 13.44
A23: Convertible Bond -2027 | D23: 5 | E23: 5 | F23: =E23 -> 5 | G23: =F23 -> 5 | H23: 0 | I23: =H23 -> 0 | J23: =I23 -> 0 | K23: Hardcoded as Conversion done in 2027
A24: Other Long-Term Liabilities | D24: 0.15 | E24: 0.1 | F24: =E24 -> 0.1 | G24: =F24 -> 0.1 | H24: =G24 -> 0.1 | I24: =H24 -> 0.1 | J24: =I24 -> 0.1
A25: Provision for warranty | E25: 0.2 | F25: =E25+INC!F44 -> 1.7034671 | G25: =F25+INC!G44 -> 3.5253868 | H25: =G25+INC!H44 -> 5.7514305 | I25: =H25+INC!I44-Instructions!E26 -> 6.4934983 | J25: =I25+INC!J44-Instructions!E27 -> 6.8986316
A26: Total Liabilities | D26: =SUM(D20,D22:D25) -> 23.58 | E26: =SUM(E20,E22:E25) -> 28.03 | F26: =SUM(F20,F22:F25) -> 41.004678 | G26: =SUM(G20,G22:G25) -> 41.682329 | H26: =SUM(H20,H22:H25) -> 38.26334 | I26: =SUM(I20,I22:I25) -> 39.012455 | J26: =SUM(J20,J22:J25) -> 40.281494
A28: Shareholders' Equity | D28: 36.02 | E28: 36.8 | F28: =F46 -> 42.284218 | G28: =G46 -> 53.416302 | H28: =H46 -> 77.2099 | I28: =I46 -> 106.67186 | J28: =J46 -> 149.459
A30: Total Liabilities and SHE | D30: =+D28+D26 -> 59.6 | E30: =+E28+E26 -> 64.83 | F30: =+F28+F26 -> 83.288896 | G30: =+G28+G26 -> 95.098631 | H30: =+H28+H26 -> 115.47324 | I30: =+I28+I26 -> 145.68431 | J30: =+J28+J26 -> 189.74049
A32: balance check | D32: =+D15-D30 -> 0 | E32: =+E15-E30 -> 0 | F32: =+F15-F30 -> 0 | G32: =+G15-G30 -> 0 | H32: =+H15-H30 -> 0 | I32: =+I15-I30 -> 0 | J32: =+J15-J30 -> 0
A35: NOTE :
A36: Particulars | D36: 2023 | E36: 2024 | F36: 2025 | G36: 2026 | H36: 2027 | I36: 2028 | J36: 2029
A37: Accounts Receivables | D37: =D7 -> 5.48 | E37: =E7 -> 5.82 | F37: =(E37/INC!E6)*INC!F6 -> 6.994547 | G37: =(F37/INC!F6)*INC!G6 -> 8.4760773 | H37: =(G37/INC!G6)*INC!H6 -> 10.356175 | I37: =(H37/INC!H6)*INC!I6 -> 12.756862 | J37: =(I37/INC!I6)*INC!J6 -> 15.841627
A38: Inventory | D38: =D8 -> 28.54 | E38: =E8 -> 31.44 | F38: =(E38/INC!E6)*INC!F6 -> 37.784975 | G38: =(F38/INC!F6)*INC!G6 -> 45.788294 | H38: =(G38/INC!G6)*INC!H6 -> 55.944696 | I38: =(H38/INC!H6)*INC!I6 -> 68.913359 | J38: =(I38/INC!I6)*INC!J6 -> 85.57745
A39: Other Current Assets | D39: =D9 -> 4.46 | E39: =E9 -> 5.69 | F39: =(E39/INC!E6)*INC!F6 -> 6.8383114 | G39: =(F39/INC!F6)*INC!G6 -> 8.2867492 | H39: =(G39/INC!G6)*INC!H6 -> 10.124851 | I39: =(H39/INC!H6)*INC!I6 -> 12.471915 | J39: =(I39/INC!I6)*INC!J6 -> 15.487776
A40: Net Block | D40: =D12 -> 17.1 | E40: =E12 -> 18.34 | F40: =E40-CFS!F20-INC!F42 -> 18.089 | G40: =F40-CFS!G20-INC!G42 -> 17.37565 | H40: =G40-CFS!H20-INC!H42 -> 13.769303 | I40: =H40-CFS!I20-INC!I42 -> 15.703907 | J40: =I40-CFS!J20-INC!J42 -> 18.848321
A41: Investment in Subsidiary | D41: =D14 -> 0 | E41: =E14 -> 0 | F41: =E41-CFS!F21 -> 5 | G41: =F41-CFS!G21 -> 5 | H41: =G41-CFS!H21 -> 5 | I41: =H41-CFS!I21 -> 3 | J41: =I41-CFS!J21 -> 0
A42: Accounts Payables | D42: =D18 -> 6.67 | E42: =E18 -> 4.79 | F42: =(E42/INC!E29)*INC!F29 -> 5.7566804 | G42: =(F42/INC!F29)*INC!G29 -> 6.9760155 | H42: =(G42/INC!G29)*INC!H29 -> 8.5233809 | I42: =(H42/INC!H29)*INC!I29 -> 10.499205 | J42: =(I42/INC!I29)*INC!J29 -> 13.03804
A43: Other Current Liabilities | D43: =D19 -> 4.12 | E43: =E19 -> 2.5 | F43: =(E43/INC!E29)*INC!F29 -> 3.0045305 | G43: =(F43/INC!F29)*INC!G29 -> 3.6409267 | H43: =(G43/INC!G29)*INC!H29 -> 4.4485286 | I43: =(H43/INC!H29)*INC!I29 -> 5.4797518 | J43: =(I43/INC!I29)*INC!J29 -> 6.8048227
A44: Debt adjusments | F44: 10 | G44: =-3 -> -3 | H44: =-3 -> -3 | I44: =-3 -> -3 | J44: =-3 -> -3
A45: Debt | D45: =D22 -> 7.64 | E45: =E22 -> 15.44 | F45: =E45+F44 -> 25.44 | G45: =F45+G44 -> 22.44 | H45: =G45+H44 -> 19.44 | I45: =H45+I44 -> 16.44 | J45: =I45+J44 -> 13.44
A46: Equity | D46: =D28 -> 36.02 | E46: =E28 -> 36.8 | F46: =E46+INC!F53-INC!F54+(E23-F23) -> 42.284218 | G46: =F46+INC!G53-INC!G54+(F23-G23) -> 53.416302 | H46: =G46+INC!H53-INC!H54+(G23-H23) -> 77.2099 | I46: =H46+INC!I53-INC!I54+(H23-I23) -> 106.67186 | J46: =I46+INC!J53-INC!J54+(I23-J23) -> 149.459

Sheet CFS
A1: =INC!A1 -> EXCEL MODELING TEST
A2: Cash Flow Statement
A3: (INR, Millions)
F4: =+BS!F4 -> 2025 | G4: =+BS!G4 -> 2026 | H4: =+BS!H4 -> 2027 | I4: =+BS!I4 -> 2028 | J4: =+BS!J4 -> 2029
A6: Cash From Operations
A7: Net Profit | F7: =INC!F53 -> 5.7728608 | G7: =INC!G53 -> 11.717984 | H7: =INC!H53 -> 19.782735 | I7: =INC!I53 -> 31.01259 | J7: =INC!J53 -> 45.039091
A8: Add: Depreciation | F8: =INC!F42 -> 2.751 | G8: =INC!G42 -> 2.71335 | H8: =INC!H42 -> 2.6063475 | I8: =INC!I42 -> 2.0653954 | J8: =INC!J42 -> 2.3555861
A9: Add: Provision | F9: =INC!F44 -> 1.5034671 | G9: =INC!G44 -> 1.8219197 | H9: =INC!H44 -> 2.2260437 | I9: =INC!I44 -> 2.7420678 | J9: =INC!J44 -> 3.4051333
A10: Less: cash paid for warranty service | I10: =-Instructions!E26 -> -2 | J10: =-Instructions!E27 -> -3
A11: (Increase)/Decrease in Receivables | F11: =BS!E7-BS!F7 -> -1.174547 | G11: =BS!F7-BS!G7 -> -1.4815304 | H11: =BS!G7-BS!H7 -> -1.8800973 | I11: =BS!H7-BS!I7 -> -2.4006876 | J11: =BS!I7-BS!J7 -> -3.0847649
A12: (Increase)/Decrease in Inventory | F12: =BS!E8-BS!F8 -> -6.3449754 | G12: =BS!F8-BS!G8 -> -8.0033186 | H12: =BS!G8-BS!H8 -> -10.156402 | I12: =BS!H8-BS!I8 -> -12.968663 | J12: =BS!I8-BS!J8 -> -16.664091
A13: (Increase)/Decrease in Other Current Assets | F13: =BS!E9-BS!F9 -> -1.1483114 | G13: =BS!F9-BS!G9 -> -1.4484378 | H13: =BS!G9-BS!H9 -> -1.838102 | I13: =BS!H9-BS!I9 -> -2.347064 | J13: =BS!I9-BS!J9 -> -3.0158612
A14: Increase/(Decrease in Accounts Payable | F14: =BS!F18-BS!E18 -> 0.96668042 | G14: =BS!G18-BS!F18 -> 1.2193351 | H14: =BS!H18-BS!G18 -> 1.5473653 | I14: =BS!I18-BS!H18 -> 1.9758236 | J14: =BS!J18-BS!I18 -> 2.5388357
A15: Increase/(Decrease in Other CL | F15: =BS!F19-BS!E19 -> 0.50453049 | G15: =BS!G19-BS!F19 -> 0.6363962 | H15: =BS!H19-BS!G19 -> 0.80760195 | I15: =BS!I19-BS!H19 -> 1.0312232 | J15: =BS!J19-BS!I19 -> 1.3250708
A17: Cash From Operations | F17: =SUM(F7:F16) -> 2.8307049 | G17: =SUM(G7:G16) -> 7.1756978 | H17: =SUM(H7:H16) -> 13.095492 | I17: =SUM(I7:I16) -> 19.110685 | J17: =SUM(J7:J16) -> 28.899001
A19: Cash (Used) in Investing Activities
A20: Capital Expenditures | F20: -2.5 | G20: -2 | H20: 1 | I20: -4 | J20: -5.5
A21: Investment in Subsidiary | F21: -5 | G21: 0 | H21: 0 | I21: =-0.4*F21 -> 2 | J21: =-0.6*F21 -> 3
A26: Cash (Used) in Investing Activities | F26: =SUM(F20:F21) -> -7.5 | G26: =SUM(G20:G21) -> -2 | H26: =SUM(H20:H21) -> 1 | I26: =SUM(I20:I21) -> -2 | J26: =SUM(J20:J21) -> -2.5
A29: Cash (Used) in Financing Activities
A30: Debt | F30: =BS!F44 -> 10
A31: Debt Repaid | G31: =BS!G44 -> -3 | H31: =BS!H44 -> -3 | I31: =BS!I44 -> -3 | J31: =BS!J44 -> -3
A32: Dividend Paid | F32: =-INC!F54 -> -0.28864304 | G32: =-INC!G54 -> -0.58589918 | H32: =-INC!H54 -> -0.98913674 | I32: =-INC!I54 -> -1.5506295 | J32: =-INC!J54 -> -2.2519546
A36: Cash (Used) in Financing Activities | F36: =SUM(F30:F35) -> 9.711357 | G36: =SUM(G31:G35) -> -3.5858992 | H36: =SUM(H31:H35) -> -3.9891367 | I36: =SUM(I31:I35) -> -4.5506295 | J36: =SUM(J31:J35) -> -5.2519546
A39: Net Cash Flow | F39: =F17+F26+F36 -> 5.0420619 | G39: =G17+G26+G36 -> 1.5897987 | H39: =H17+H26+H36 -> 10.106355 | I39: =I17+I26+I36 -> 12.560056 | J39: =J17+J26+J36 -> 21.147046
A41: Beginning Cash Balance | F41: =BS!E6 -> 1.03 | G41: =F42 -> 6.0720619 | H41: =G42 -> 7.6618606 | I41: =H42 -> 17.768216 | J41: =I42 -> 30.328271
A42: Ending Cash Balance | F42: =F41+F39 -> 6.0720619 | G42: =G41+G39 -> 7.6618606 | H42: =H41+H39 -> 17.768216 | I42: =I41+I39 -> 30.328271 | J42: =J41+J39 -> 51.475317
A45: NOTE:
A46: Particulars | F46: 2025 | G46: 2026 | H46: 2027 | I46: 2028 | J46: 2029
A47: Working Capital Changes | F47: =SUM(F11:F15) -> -7.1966229 | G47: =SUM(G11:G15) -> -9.0775554 | H47: =SUM(H11:H15) -> -11.519634 | I47: =SUM(I11:I15) -> -14.709368 | J47: =SUM(J11:J15) -> -18.90081

Sheet Ratios
A1: =INC!A1 -> EXCEL MODELING TEST
A2: Key Ratios
A3: (INR, Millions)
F4: =+INC!F4 -> 2025 | G4: =+INC!G4 -> 2026 | H4: =+INC!H4 -> 2027 | I4: =+INC!I4 -> 2028 | J4: =+INC!J4 -> 2029
A6: Net Sales Growth % | F6: =(INC!F6/INC!E6)-1 -> 0.2018122 | G6: =(INC!G6/INC!F6)-1 -> 0.2118122 | H6: =(INC!H6/INC!G6)-1 -> 0.2218122 | I6: =(INC!I6/INC!H6)-1 -> 0.2318122 | J6: =(INC!J6/INC!I6)-1 -> 0.2418122
A7: Gross Profit Margin | F7: =INC!F33/INC!F29 -> 0.357339 | G7: =INC!G33/INC!G29 -> 0.36857204 | H7: =INC!H33/INC!H29 -> 0.37716942 | I7: =INC!I33/INC!I29 -> 0.38596011 | J7: =INC!J33/INC!J29 -> 0.39492779
A8: EBIT Margin | F8: =INC!F46/INC!F29 -> 0.064369511 | G8: =INC!G46/INC!G29 -> 0.10190557 | H8: =INC!H46/INC!H29 -> 0.13435248 | I8: =INC!I46/INC!I29 -> 0.16582412 | J8: =INC!J46/INC!J29 -> 0.1918514
A9: Net Profit Margin | F9: =INC!F53/INC!F29 -> 0.038396989 | G9: =INC!G53/INC!G29 -> 0.064316684 | H9: =INC!H53/INC!H29 -> 0.088869479 | I9: =INC!I53/INC!I29 -> 0.11309928 | J9: =INC!J53/INC!J29 -> 0.13226822
A10: Interest Coverage Ratio | F10: =INC!F46/INC!F48 -> 6.7638692 | G10: =INC!G46/INC!G48 -> 10.165559 | H10: =INC!H46/INC!H48 -> 18.165361 | I10: =INC!I46/INC!I48 -> 38.983282 | J10: =INC!J46/INC!J48 -> 66.228669
A11: Debt Service Coverage Ratio | F11: =(INC!F53+INC!F42+INC!F48)/(INC!F48+MAX(-BS!F44,0)) -> 6.957409 | G11: =(INC!G53+INC!G42+INC!G48)/(INC!G48+MAX(-BS!G44,0)) -> 3.3685011 | H11: =(INC!H53+INC!H42+INC!H48)/(INC!H48+MAX(-BS!H44,0)) -> 5.1729258 | I11: =(INC!I53+INC!I42+INC!I48)/(INC!I48+MAX(-BS!I44,0)) -> 8.2191784 | J11: =(INC!J53+INC!J42+INC!J48)/(INC!J48+MAX(-BS!J44,0)) -> 12.136534
A12: Retention Ratio | F12: =1-(INC!F54/INC!F53) -> 0.95 | G12: =1-(INC!G54/INC!G53) -> 0.95 | H12: =1-(INC!H54/INC!H53) -> 0.95 | I12: =1-(INC!I54/INC!I53) -> 0.95 | J12: =1-(INC!J54/INC!J53) -> 0.95
A13: Current Ratio | F13: =BS!F10/BS!F20 -> 6.5846943 | G13: =BS!G10/BS!G20 -> 6.613296 | H13: =BS!H10/BS!H20 -> 7.2613779 | I13: =BS!I10/BS!I20 -> 7.7896457 | J13: =BS!J10/BS!J20 -> 8.4857801
A14: Receivable Days | F14: =(BS!F7/INC!F29)*365 -> 16.980815 | G14: =(BS!G7/INC!G29)*365 -> 16.980815 | H14: =(BS!H7/INC!H29)*365 -> 16.980815 | I14: =(BS!I7/INC!I29)*365 -> 16.980815 | J14: =(BS!J7/INC!J29)*365 -> 16.980815
A15: Debt Equity | F15: =(BS!F22+BS!F23)/BS!F28 -> 0.71989034 | G15: =(BS!G22+BS!G23)/BS!G28 -> 0.51370085 | H15: =(BS!H22+BS!H23)/BS!H28 -> 0.25178118 | I15: =(BS!I22+BS!I23)/BS!I28 -> 0.1541175 | J15: =(BS!J22+BS!J23)/BS!J28 -> 0.089924329
A16: Book Value (INR million) | F16: =BS!F28 -> 42.284218 | G16: =BS!G28 -> 53.416302 | H16: =BS!H28 -> 77.2099 | I16: =BS!I28 -> 106.67186 | J16: =BS!J28 -> 149.459
A17: Return on Capital Employed | F17: =INC!F46/(BS!F15-BS!F20) -> 0.12985435 | G17: =INC!G46/(BS!G15-BS!G20) -> 0.21976806 | H17: =INC!H46/(BS!H15-BS!H20) -> 0.29177621 | I17: =INC!I46/(BS!I15-BS!I20) -> 0.35056454 | J17: =INC!J46/(BS!J15-BS!J20) -> 0.38451366
A18: Return on Equity | F18: =INC!F53/BS!F28 -> 0.13652519 | G18: =INC!G53/BS!G28 -> 0.21937092 | H18: =INC!H53/BS!H28 -> 0.25622018 | I18: =INC!I53/BS!I28 -> 0.29072887 | J18: =INC!J53/BS!J28 -> 0.30134748

Sheet FCFF Valuation
A1: =INC!A1 -> EXCEL MODELING TEST
A2: FCFF Valuation
A3: (INR, Millions)
F4: =+INC!F4 -> 2025 | G4: =+INC!G4 -> 2026 | H4: =+INC!H4 -> 2027 | I4: =+INC!I4 -> 2028 | J4: =+INC!J4 -> 2029
A7: Beta to beused for stock | B7: 1.2
A8: Riskfree rate (Rf) | B8: 0.0325
A9: Market Rate of Return (Rm) | B9: 0.103
A10: Growth Rate | B10: 0.03
A11: Tax | B11: =Instructions!$E$29 -> 0.3
A13: Cost of Equity | F13: =B8+B7*(B9-B8) -> 0.1171 | G13: =F13 -> 0.1171 | H13: =G13 -> 0.1171 | I13: =H13 -> 0.1171 | J13: =I13 -> 0.1171
A14: Pre Tax Cost of Debt | F14: =INC!F48/(BS!E22+BS!E23) -> 0.07 | G14: =INC!G48/(BS!F22+BS!F23) -> 0.06 | H14: =INC!H48/(BS!G22+BS!G23) -> 0.06 | I14: =INC!I48/(BS!H22+BS!H23) -> 0.06 | J14: =INC!J48/(BS!I22+BS!I23) -> 0.06
A15: Post Tax Cost of Debt | F15: =F14*(1-$B$11) -> 0.049 | G15: =G14*(1-$B$11) -> 0.042 | H15: =H14*(1-$B$11) -> 0.042 | I15: =I14*(1-$B$11) -> 0.042 | J15: =J14*(1-$B$11) -> 0.042
A16: Equity | F16: =BS!F28 -> 42.284218 | G16: =BS!G28 -> 53.416302 | H16: =BS!H28 -> 77.2099 | I16: =BS!I28 -> 106.67186 | J16: =BS!J28 -> 149.459
A17: Debt | F17: =SUM(BS!F22:F23) -> 30.44 | G17: =SUM(BS!G22:G23) -> 27.44 | H17: =SUM(BS!H22:H23) -> 19.44 | I17: =SUM(BS!I22:I23) -> 16.44 | J17: =SUM(BS!J22:J23) -> 13.44
A18: Total Value | F18: =SUM(F16:F17) -> 72.724218 | G18: =SUM(G16:G17) -> 80.856302 | H18: =SUM(H16:H17) -> 96.6499 | I18: =SUM(I16:I17) -> 123.11186 | J18: =SUM(J16:J17) -> 162.899
A19: Equity Weight | F19: =F16/F18 -> 0.58143242 | G19: =G16/G18 -> 0.66063251 | H19: =H16/H18 -> 0.79886166 | I19: =I16/I18 -> 0.86646291 | J19: =J16/J18 -> 0.91749489
A20: Debt Weight | F20: =F17/F18 -> 0.41856758 | G20: =G17/G18 -> 0.33936749 | H20: =H17/H18 -> 0.20113834 | I20: =I17/I18 -> 0.13353709 | J20: =J17/J18 -> 0.082505112
A21: WACC | F21: =(F13*F19)+(F15*F20) -> 0.088595548 | G21: =(G13*G19)+(G15*G20) -> 0.091613502 | H21: =(H13*H19)+(H15*H20) -> 0.10199451 | I21: =(I13*I19)+(I15*I20) -> 0.10707136 | J21: =(J13*J19)+(J15*J20) -> 0.11090387
A23: EBIT | F23: =INC!F46 -> 9.677744 | G23: =INC!G46 -> 18.566376 | H23: =INC!H46 -> 29.90745 | I23: =INC!I46 -> 45.4701 | J23: =INC!J46 -> 65.327959
A24: Tax on EBIT | F24: =F23*$B$11 -> 2.9033232 | G24: =G23*$B$11 -> 5.5699129 | H24: =H23*$B$11 -> 8.9722349 | I24: =I23*$B$11 -> 13.64103 | J24: =J23*$B$11 -> 19.598388
A25: NOPAT | F25: =F23-F24 -> 6.7744208 | G25: =G23-G24 -> 12.996464 | H25: =H23-H24 -> 20.935215 | I25: =I23-I24 -> 31.82907 | J25: =J23-J24 -> 45.729571
A26: Depriciation | F26: =INC!F42 -> 2.751 | G26: =INC!G42 -> 2.71335 | H26: =INC!H42 -> 2.6063475 | I26: =INC!I42 -> 2.0653954 | J26: =INC!J42 -> 2.3555861
A27: Provision for warranty | F27: =INC!F44 -> 1.5034671 | G27: =INC!G44 -> 1.8219197 | H27: =INC!H44 -> 2.2260437 | I27: =INC!I44 -> 2.7420678 | J27: =INC!J44 -> 3.4051333
A28: Cash Paid For warranty | F28: =CFS!F10 -> 0 | G28: =CFS!G10 -> 0 | H28: =CFS!H10 -> 0 | I28: =CFS!I10 -> -2 | J28: =CFS!J10 -> -3
A29: Capex | F29: =CFS!F20 -> -2.5 | G29: =CFS!G20 -> -2 | H29: =CFS!H20 -> 1 | I29: =CFS!I20 -> -4 | J29: =CFS!J20 -> -5.5
A30: WCC | F30: =CFS!F47 -> -7.1966229 | G30: =CFS!G47 -> -9.0775554 | H30: =CFS!H47 -> -11.519634 | I30: =CFS!I47 -> -14.709368 | J30: =CFS!J47 -> -18.90081
A31: FCFF | F31: =SUM(F25:F30) -> 1.3322649 | G31: =SUM(G25:G30) -> 6.4541778 | H31: =SUM(H25:H30) -> 15.247972 | I31: =SUM(I25:I30) -> 15.927165 | J31: =SUM(J25:J30) -> 24.089481
A33: Discount Factor | F33: =1/(1+F21) -> 0.91861482 | G33: =F33/(1+G21) -> 0.8415202 | H33: =G33/(1+H21) -> 0.76363375 | I33: =H33/(1+I21) -> 0.68977825 | J33: =I33/(1+J21) -> 0.62091624
A34: PV of FCFF | F34: =F33*F31 -> 1.2238383 | G34: =G33*G31 -> 5.4313211 | H34: =H33*H31 -> 11.643866 | I34: =I33*I31 -> 10.986212 | J34: =J33*J31 -> 14.95755 | L34: Sum of PV | M34: =SUM(F34:J34) -> 44.242787
A35: Terminal Value | J35: =J31*(1+$B$10)/(J21-$B$10) -> 306.68701
A36: PV of Terminal Value | J36: =J35*J33 -> 190.42695
A37: Enterprise Value | B37: =M34+J36 -> 234.66973
A38: Net Debt | B38: =BS!E22+BS!E23-BS!E6 -> 19.41
A39: Equity Value | B39: =B37-B38 -> 215.25973

Sheet Instructions
A2: Income Statement | G2: Working Capital and Balance Sheet
A4: Net Sales
A5: For 2025 - Sales grows by the CAGR of 2007-10 plus - | E5: 0.02 | G5: Working capital: Use the same proportions as a percentage
A6: For 2026 to 2029 - Sales grows at previous year's growth plus - | E6: 0.01 | G6: of revenues as observed in previous year
G7: Other Long-term Assets: Keep flat.
A8: Cost of Goods Sold (COGS) | G8: Other Long-term Liabilities: Keep flat.
A9: C O G S Growth /Net Sales Growth ('11 & '12) | E9: 0.9 | G9: Debt: Company takes additional debt of US$10 million in 2025 & repays US$3 million every year from 2026 to 29
A10: (ie, if sales grows by 100%, COGS grows by90%) | G10: Convertible bond gets converted at the year mentioned with it
A11: C O G S growth /Net Sales Growth ('13 to '15) | E11: 0.925 | G11: Dividend Payout ratio as % of net income | K11: 0.05
A12: (ie, if sales grows by 100%, COGS grows by 92.5%) | G12: Investment in subsidiary: The company would buy controlling stake in a company in 2025
G13: for US$5 mn. It would sell 40% of it at cost in 2027 and remaining stake in 2029 at cost.
A14: SG&A
A15: Fixed SG&A growth rate/Net Sales Growth | E15: 0.25
A16: (ie, if sales grows by 10%, fixed SG&A grows by 2.5%)
A18: Variable SG&A as % of Net Sales | E18: 0.09
A20: Depreciation on Opening Net Block | E20: 0.15
A22: Provision for warranty (as a % of Net Sales) | E22: 0.01
A24: Warranty service: The company is expected to incur the following
A25: cash expenditure for repair of products under warranty
A26: 2028 | E26: 2
A27: 2029 | E27: 3
A29: Tax Rate (every year) | E29: 0.3
A32: Interest Expense (on debt + convertible bond)
A34: Condition 1:
A35: Use beginning of year balance to calculate interest expense at | E35: 0.06
A36: Condition 2:
A37: If Interest coverage falls below 6 times, calculate interest expense
A38: for next year at | E38: 0.07
