Workbook

Sheet ABOUT THE COMPANY
A1: TITAN COMPANY (TAANISHQ)
A3: According to the Management Discussion and Analysis section of Titan Company Limited’s recent Annual Reports, the company has shown consistent growth across all its business segments. In FY 2024-25, Titan achieved a total consolidated income of ₹57,818 crore, marking a 22% increase over the previous year, while the Q4 FY 25 income stood at ₹12,730 crore, also reflecting a 22% year-on-year growth. The Jewellery Division, which remains Titan’s largest business, recorded a total income of ₹46,571 crore, growing by nearly 21% during the year. Its EBIT stood at ₹4,764 crore, with a margin of about 10.2%, although management acknowledged some margin pressure due to fluctuations in gold prices and changes in customs duty. The Watches and Wearables Division continued its strong performance, registering 46% growth in Net Sales Value in FY 2021-22 and achieving 19% of its total sales through online channels, indicating Titan’s successful digital expansion. The company’s Reserves & Surplus stood at ₹16,722 crore as of March 2025, while short-term borrowings were reported at ₹14,526 crore, reflecting a balanced capital structure. The management emphasised that, despite pandemic-related disruptions and inflationary challenges, all business units exceeded their internal targets through a focus on premiumisation, omnichannel retailing, and customer-centric innovation. Overall, the MDA highlights Titan’s strong operational performance, strategic agility, and readiness to capture growth opportunities in India’s evolving consumer market.

Sheet PROFIT & LOSS
B1: 43525 | C1: 43891 | D1: 44256 | E1: 44621 | F1: 44986 | G1: 45352 | H1: 45717 | I1: TTM
A2: Sales - | B2: 19070 | C2: 20010 | D2: 20602 | E2: 27210 | F2: 38270 | G2: 47114 | H2: 54842 | I2: 57353
A3: Sales Growth % | B3: 0.2208 | C3: 0.0493 | D3: 0.0296 | E3: 0.3207 | F3: 0.4065 | G3: 0.2311 | H3: 0.164
A4: Expenses - | B4: 17064 | C4: 17592 | D4: 18896 | E4: 23928 | F4: 33497 | G4: 42090 | H4: 49550 | I4: 51640
A5: Material Cost % - | B5: 0.73 | C5: 0.73 | D5: 0.77 | E5: 0.76 | F5: 0.76 | G5: 0.78 | H5: 0.8
A6: Raw material cost | B6: 14651 | C6: 15348 | D6: 15605 | E6: 25126 | F6: 30523 | G6: 39091 | H6: 50277
A7: Change in inventory | B7: -664 | C7: -836 | D7: 164 | E7: -4468 | F7: -1477 | G7: -2149 | H7: -6537
A8: Manufacturing Cost % | B8: 0.01 | C8: 0.01 | D8: 0.01 | E8: 0.01 | F8: 0.01 | G8: 0.01 | H8: 0.01
A9: Employee Cost % | B9: 0.05 | C9: 0.05 | D9: 0.04 | E9: 0.04 | F9: 0.04 | G9: 0.03 | H9: 0.03
A10: Other Cost % | B10: 0.1 | C10: 0.09 | D10: 0.1 | E10: 0.07 | F10: 0.07 | G10: 0.07 | H10: 0.07
A11: Operating Profit | B11: 2006 | C11: 2418 | D11: 1706 | E11: 3282 | F11: 4773 | G11: 5024 | H11: 5292 | I11: 5713
A12: OPM % | B12: 0.11 | C12: 0.12 | D12: 0.08 | E12: 0.12 | F12: 0.12 | G12: 0.11 | H12: 0.1 | I12: 0.1
A13: Other Income - | B13: 104 | C13: 146 | D13: 39 | E13: 192 | F13: 296 | G13: 510 | H13: 493 | I13: 482
A14: Exceptional items | B14: -74 | C14: 0 | D14: -138 | E14: -54 | F14: -3 | G14: 0 | H14: 0
A15: Other income normal | B15: 178 | C15: 146 | D15: 177 | E15: 246 | F15: 299 | G15: 510 | H15: 493
A16: Interest | B16: 44 | C16: 149 | D16: 181 | E16: 195 | F16: 240 | G16: 480 | H16: 767 | I16: 801
A17: Depreciation | B17: 139 | C17: 310 | D17: 331 | E17: 347 | F17: 364 | G17: 447 | H17: 537 | I17: 554
A18: Profit before tax | B18: 1927 | C18: 2105 | D18: 1233 | E18: 2932 | F18: 4465 | G18: 4607 | H18: 4481 | I18: 4840
A19: Tax % | B19: 0.29 | C19: 0.28 | D19: 0.29 | E19: 0.26 | F19: 0.25 | G19: 0.23 | H19: 0.26
A20: Net Profit - | B20: 1374 | C20: 1517 | D20: 877 | E20: 2180 | F20: 3333 | G20: 3544 | H20: 3335 | I20: 3595
A21: Exceptional items AT | B21: -51 | C21: 0 | D21: -98 | E21: -40 | F21: -2 | G21: 0 | H21: 0
A22: Profit excl Excep | B22: 1425 | C22: 1517 | D22: 975 | E22: 2220 | F22: 3335 | G22: 3544 | H22: 3335
A23: Profit for PE | B23: 1425 | C23: 1517 | D23: 975 | E23: 2220 | F23: 3335 | G23: 3544 | H23: 3335
A24: Profit for EPS | B24: 1374 | C24: 1517 | D24: 877 | E24: 2180 | F24: 3333 | G24: 3544 | H24: 3335
A25: EPS in Rs | B25: 15.48 | C25: 17.09 | D25: 9.88 | E25: 24.56 | F25: 37.54 | G25: 39.92 | H25: 37.57 | I25: 40.49
A26: Dividend Payout % | B26: 0.32 | C26: 0.23 | D26: 0.41 | E26: 0.31 | F26: 0.27 | G26: 0.28 | H26: 0.29

Sheet BALANCE SHEET
B1: 43525 | C1: 43891 | D1: 44256 | E1: 44621 | F1: 44986 | G1: 45352 | H1: 45717
A2: Equity Capital | B2: 89 | C2: 89 | D2: 89 | E2: 89 | F2: 89 | G2: 89 | H2: 89
A3: Reserves | B3: 6093 | C3: 6736 | D3: 7464 | E3: 9284 | F3: 11905 | G3: 14368 | H3: 16722
A4: Total Equity | B4: =SUM(B2:B3) -> 6182 | C4: =SUM(C2:C3) -> 6825 | D4: =SUM(D2:D3) -> 7553 | E4: =SUM(E2:E3) -> 9373 | F4: =SUM(F2:F3) -> 11994 | G4: =SUM(G2:G3) -> 14457 | H4: =SUM(H2:H3) -> 16811
A5: Borrowings - | B5: 2288 | C5: 3269 | D5: 5243 | E5: 6605 | F5: 7862 | G5: 12661 | H5: 17171
A6: Long term Borrowings | B6: 0 | C6: 0 | D6: 0 | E6: 0 | F6: 0 | G6: 3139 | H6: 420
A7: Short term Borrowings | B7: 2288 | C7: 2133 | D7: 4094 | E7: 5386 | F7: 6280 | G7: 7608 | H7: 14526
A8: Lease Liabilities | B8: 0 | C8: 1136 | D8: 1149 | E8: 1219 | F8: 1582 | G8: 1914 | H8: 2225
A9: Other Liabilities - | B9: 3000 | C9: 3094 | D9: 3064 | E9: 4159 | F9: 5232 | G9: 5744 | H9: 7093
A10: Trade Payables | B10: 772 | C10: 510 | D10: 695 | E10: 1055 | F10: 965 | G10: 943 | H10: 1472
A11: Advance from Customers | B11: 237 | C11: 309 | D11: 388 | E11: 420 | F11: 597 | G11: 834 | H11: 1840
A12: Other liability items | B12: 1991 | C12: 2275 | D12: 1981 | E12: 2684 | F12: 3670 | G12: 3967 | H12: 3781
A13: Total Current Liability | B13: =SUM(B10:B12) -> 3000 | C13: =SUM(C10:C12) -> 3094 | D13: =SUM(D10:D12) -> 3064 | E13: =SUM(E10:E12) -> 4159 | F13: =SUM(F10:F12) -> 5232 | G13: =SUM(G10:G12) -> 5744 | H13: =SUM(H10:H12) -> 7093
A14: Total Liabilities | B14: 11470 | C14: 13188 | D14: 15860 | E14: 20137 | F14: 25088 | G14: 32862 | H14: 41075
A15: Fixed Assets - | B15: 1069 | C15: 2053 | D15: 1959 | E15: 1925 | F15: 2161 | G15: 2691 | H15: 3019
A16: Land | B16: 79 | C16: 100 | D16: 100 | E16: 123 | F16: 123 | G16: 123 | H16: 123
A17: Building | B17: 321 | C17: 1341 | D17: 1464 | E17: 1636 | F17: 1982 | G17: 2957 | H17: 3517
A18: Plant Machinery | B18: 508 | C18: 574 | D18: 583 | E18: 610 | F18: 662 | G18: 666 | H18: 738
A19: Equipments | B19: 42 | C19: 60 | D19: 66 | E19: 77 | F19: 99 | G19: 68 | H19: 81
A20: Computers | B20: 83 | C20: 106 | D20: 126 | E20: 140 | F20: 173 | G20: 175 | H20: 190
A21: Furniture n fittings | B21: 234 | C21: 293 | D21: 294 | E21: 303 | F21: 350 | G21: 138 | H21: 152
A22: Vehicles | B22: 20 | C22: 25 | D22: 26 | E22: 34 | F22: 36 | G22: 45 | H22: 51
A23: Intangible Assets | B23: 3 | C23: 17 | D23: 17 | E23: 17 | F23: 17 | G23: 17 | H23: 17
A24: Other fixed assets | B24: 86 | C24: 118 | D24: 137 | E24: 123 | F24: 145 | G24: 220 | H24: 269
A25: Gross Block | B25: 1376 | C25: 2634 | D25: 2813 | E25: 3063 | F25: 3587 | G25: 4409 | H25: 5138
... A30: Inventories | B30: 6719 | C30: 7741 | D30: 7984 | E30: 12787 | F30: 14952 | G30: 16874 | H30: 24517
A31: inventory % | B31: =B30/100 -> 67.19 | C31: =C30/100 -> 77.41 | D31: =D30/100 -> 79.84 | E31: =E30/100 -> 127.87 | F31: =F30/100 -> 149.52 | G31: =G30/100 -> 168.74 | H31: =H30/100 -> 245.17
A32: Trade receivables | B32: 358 | C32: 214 | D32: 291 | E32: 495 | F32: 908 | G32: 937 | H32: 984
A33: Cash Equivalents | B33: 1001 | C33: 356 | D33: 512 | E33: 1049 | F33: 792 | G33: 805 | H33: 1132
A34: Loans n Advances | B34: 13 | C34: -17 | D34: -50 | E34: 4 | F34: 116 | G34: 65 | H34: 262
A35: Other asset items | B35: 1407 | C35: 1844 | D35: 1627 | E35: 2922 | F35: 2773 | G35: 3590 | H35: 3344
A36: Total Current Assets | B36: =SUM(B30:B35) -> 9565.19 | C36: =SUM(C30:C35) -> 10215.41 | D36: =SUM(D30:D35) -> 10443.84 | E36: =SUM(E30:E35) -> 17384.87 | F36: =SUM(F30:F35) -> 19690.52 | G36: =SUM(G30:G35) -> 22439.74 | H36: =SUM(H30:H35) -> 30484.17
A37: Total Assets | B37: 11470 | C37: 13188 | D37: 15860 | E37: 20137 | F37: 25088 | G37: 32862 | H37: 41075

Sheet CASH FLOW STATEMENT
A1: PARTICULARS | B1: 43525 | C1: 43891 | D1: 44256 | E1: 44621 | F1: 44986 | G1: 45352 | H1: 45717
A2: Cash from Operating Activity - | B2: 1249 | C2: -289 | D2: 4101 | E2: -1126 | F2: 1810 | G2: 2030 | H2: -170
A3: Profit from operations | B3: 2179 | C3: 2425 | D3: 1719 | E3: 3224 | F3: 4814 | G3: 5116 | H3: 5358
A4: Receivables | B4: -164 | C4: 144 | D4: -78 | E4: -204 | F4: -414 | G4: -22 | H4: -61
A5: Inventory | B5: -970 | C5: -1021 | D5: -243 | E5: -4803 | F5: -2165 | G5: -1922 | H5: -7643
A6: Payables | B6: -14 | C6: -263 | D6: 187 | E6: 362 | F6: -89 | G6: -24 | H6: 539
A7: Loans Advances | B7: -21 | C7: -16 | D7: -6 | E7: -1 | F7: -17 | G7: -8 | H7: -312
A8: Operating borrowings | B8: 684 | C8: -781 | D8: 2587 | E8: 1067 | F8: -71 | G8: -152 | H8: 2105
A9: Other WC items | B9: 177 | C9: -240 | D9: 198 | E9: 25 | F9: 894 | G9: 182 | H9: 866
A10: Working capital changes | B10: -309 | C10: -2177 | D10: 2645 | E10: -3554 | F10: -1862 | G10: -1946 | H10: -4506
A11: Direct taxes | B11: -622 | C11: -537 | D11: -263 | E11: -796 | F11: -1142 | G11: -1140 | H11: -1022
A12: Cash from Investing Activity - | B12: -910 | C12: 243 | D12: -2744 | E12: 1564 | F12: -1653 | G12: -4634 | H12: 140
... A31: Net Cash Flow | B31: -102 | C31: -314 | D31: 97 | E31: -30 | F31: 2 | G31: 153 | H31: -29

Sheet KEY RATIO ANALYSIS
A1: S.No. | B1: Ratio Name | C1: Formula | D1: 43891 | E1: 44256 | F1: 44621 | G1: 44986 | H1: 45352 | I1: 45717 | J1: SPARKLINES | K1: INTERPRETATIONS
A2: 1 | B2: Return on Sales (ROS) | C2: Net Income / Net Sales | D2: ='PROFIT & LOSS'!C20/'PROFIT & LOSS'!C2 -> 0.075812094 | E2: ='PROFIT & LOSS'!D20/'PROFIT & LOSS'!D2 -> 0.042568683 | F2: ='PROFIT & LOSS'!E20/'PROFIT & LOSS'!E2 -> 0.080117604 | G2: ='PROFIT & LOSS'!F20/'PROFIT & LOSS'!F2 -> 0.087091717 | H2: ='PROFIT & LOSS'!G20/'PROFIT & LOSS'!G2 -> 0.075221802 | I2: ='PROFIT & LOSS'!H20/'PROFIT & LOSS'!H2 -> 0.060811057 | K2: It fell from 7.6% in 2020 to 6.0% in 2025, meaning sales are earning slightly less profit now, the company is making less money from each rupee of sales.
A3: 2 | B3: Asset Turnover | C3: Net Sales / Total Assets | D3: ='PROFIT & LOSS'!C20/'BALANCE SHEET'!C37 -> 0.11502881 | E3: ='PROFIT & LOSS'!D20/'BALANCE SHEET'!D37 -> 0.055296343 | F3: ='PROFIT & LOSS'!E20/'BALANCE SHEET'!E37 -> 0.10825843 | G3: ='PROFIT & LOSS'!F20/'BALANCE SHEET'!F37 -> 0.13285236 | H3: ='PROFIT & LOSS'!G20/'BALANCE SHEET'!G37 -> 0.10784493 | I3: ='PROFIT & LOSS'!H20/'BALANCE SHEET'!H37 -> 0.08119294 | K3: It dropped from 0.12 to 0.08, showing that Titan is using its assets less efficiently to generate sales, assets are not producing as much revenue as before.
A4: 3 | B4: Return on Assets (ROA) | C4: Net Income / Total Assets or ROS × Asset Turnover | D4: =D2*D3 -> 0.0087205753 | E4: =E2*E3 -> 0.0023538925 | F4: =F2*F3 -> 0.008673406 | G4: =G2*G3 -> 0.01157034 | H4: =H2*H3 -> 0.0081122898 | I4: =I2*I3 -> 0.0049374285 | K4: It stayed around 0.8%, showing Titan’s assets are giving a small return, and efficiency hasn’t improved much over the years.
A5: 4 | B5: Financial Leverage | C5: Total Assets / Total Owners’ Equity | D5: ='BALANCE SHEET'!C37/'BALANCE SHEET'!C4 -> 1.9323077 | E5: ='BALANCE SHEET'!D37/'BALANCE SHEET'!D4 -> 2.0998279 | F5: ='BALANCE SHEET'!E37/'BALANCE SHEET'!E4 -> 2.148405 | G5: ='BALANCE SHEET'!F37/'BALANCE SHEET'!F4 -> 2.0917125 | H5: ='BALANCE SHEET'!G37/'BALANCE SHEET'!G4 -> 2.2730857 | I5: ='BALANCE SHEET'!H37/'BALANCE SHEET'!H4 -> 2.4433407 | K5: It went up from 1.93 to 2.44, meaning Titan is using more borrowed money or outside funds to support its assets, increasing both returns and financial risk.
A6: 5 | B6: Return on Equity (ROE) | C6: Net Income / Total Owners’ Equity or ROA × Financial Leverage | D6: =D4*D5 -> 0.016850835 | E6: =E4*E5 -> 0.0049427691 | F6: =F4*F5 -> 0.018633989 | G6: =G4*G5 -> 0.024201825 | H6: =H4*H5 -> 0.01843993 | I6: =I4*I5 -> 0.01206382 | K6: It increased from 1.6% to 2.1%, showing Titan is slightly better at earning profit from shareholders’ money compared to earlier years.
A7: 6 | B7: Current Ratio | C7: Total Current Assets / Total Current Liabilities | D7: ='BALANCE SHEET'!C36/'BALANCE SHEET'!C13 -> 3.3016839 | E7: ='BALANCE SHEET'!D36/'BALANCE SHEET'!D13 -> 3.408564 | F7: ='BALANCE SHEET'!E36/'BALANCE SHEET'!E13 -> 4.1800601 | G7: ='BALANCE SHEET'!F36/'BALANCE SHEET'!F13 -> 3.7634786 | H7: ='BALANCE SHEET'!G36/'BALANCE SHEET'!G13 -> 3.90664 | I7: ='BALANCE SHEET'!H36/'BALANCE SHEET'!H13 -> 4.2977823 | K7: It improved from 3.3 to 4.3, meaning Titan’s short-term assets are more than enough to pay short-term debts very strong liquidity position.
A8: 7 | B8: Inventory Turnover | C8: Cost of Goods Sold / Ending Inventory | D8: =('PROFIT & LOSS'!C5+'PROFIT & LOSS'!C8)/'BALANCE SHEET'!C31 -> 0.0095594884 | E8: =('PROFIT & LOSS'!D5+'PROFIT & LOSS'!D8)/'BALANCE SHEET'!D31 -> 0.0097695391 | F8: =('PROFIT & LOSS'!E5+'PROFIT & LOSS'!E8)/'BALANCE SHEET'!E31 -> 0.0060217408 | G8: =('PROFIT & LOSS'!F5+'PROFIT & LOSS'!F8)/'BALANCE SHEET'!F31 -> 0.0051498127 | H8: =('PROFIT & LOSS'!G5+'PROFIT & LOSS'!G8)/'BALANCE SHEET'!G31 -> 0.0046817589 | I8: =('PROFIT & LOSS'!H5+'PROFIT & LOSS'!H8)/'BALANCE SHEET'!H31 -> 0.00330383 | K8: It fell from 0.0096 to 0.0033, which means Titan is taking longer to sell its stock inventory is moving slowly, maybe because of higher stock levels or slower sales.
A9: 8 | B9: Receivables Collection Period | C9: Accounts Receivable / (Net Sales / 365 days) | D9: ='BALANCE SHEET'!C32/('PROFIT & LOSS'!C2/365) -> 3.9035482 | E9: ='BALANCE SHEET'!D32/('PROFIT & LOSS'!D2/365) -> 5.1555674 | F9: ='BALANCE SHEET'!E32/('PROFIT & LOSS'!E2/365) -> 6.6400221 | G9: ='BALANCE SHEET'!F32/('PROFIT & LOSS'!F2/365) -> 8.660047 | H9: ='BALANCE SHEET'!G32/('PROFIT & LOSS'!G2/365) -> 7.259095 | I9: ='BALANCE SHEET'!H32/('PROFIT & LOSS'!H2/365) -> 6.5489953 | K9: It rose from 3.9 days to 6.5 days, showing Titan is taking a bit longer to collect cash from customers, though still within a short period, collection efficiency slightly reduced.
A10: 9 | B10: Revenue Growth | C10: (This Year’s Net Sales − Last Year’s Net Sales) / Last Year’s Net Sales | D10: ='PROFIT & LOSS'!C3 -> 0.0493 | E10: ='PROFIT & LOSS'!D3 -> 0.0296 | F10: ='PROFIT & LOSS'!E3 -> 0.3207 | G10: ='PROFIT & LOSS'!F3 -> 0.4065 | H10: ='PROFIT & LOSS'!G3 -> 0.2311 | I10: ='PROFIT & LOSS'!H3 -> 0.164 | K10: It was highest at 32% in 2022 and came down to 16% in 2025, meaning Titan’s sales are still growing, but not as fast as before.
A11: 10 | B11: Gross Margin | C11: (Net Sales − Cost of Goods Sold) / Net Sales | D11: =('PROFIT & LOSS'!C2-'PROFIT & LOSS'!C6)/'PROFIT & LOSS'!C2 -> 0.23298351 | E11: =('PROFIT & LOSS'!D2-'PROFIT & LOSS'!D6)/'PROFIT & LOSS'!D2 -> 0.24254927 | F11: =('PROFIT & LOSS'!E2-'PROFIT & LOSS'!E6)/'PROFIT & LOSS'!E2 -> 0.076589489 | G11: =('PROFIT & LOSS'!F2-'PROFIT & LOSS'!F6)/'PROFIT & LOSS'!F2 -> 0.2024301 | H11: =('PROFIT & LOSS'!G2-'PROFIT & LOSS'!G6)/'PROFIT & LOSS'!G2 -> 0.17028909 | I11: =('PROFIT & LOSS'!H2-'PROFIT & LOSS'!H6)/'PROFIT & LOSS'!H2 -> 0.083239123 | K11: It dropped from 23% in 2020 to 8% in 2025, showing costs have increased the company is earning less profit from each rupee of sales after covering product costs.
A12: 11 | B12: Dividend Payout Ratio | C12: Cash Dividends / Net Income | D12: ='PROFIT & LOSS'!C26 -> 0.23 | E12: ='PROFIT & LOSS'!D26 -> 0.41 | F12: ='PROFIT & LOSS'!E26 -> 0.31 | G12: ='PROFIT & LOSS'!F26 -> 0.27 | H12: ='PROFIT & LOSS'!G26 -> 0.28 | I12: ='PROFIT & LOSS'!H26 -> 0.29 | K12: It remained between 23% and 41%, ending at 29%, showing Titan is consistently sharing profits with shareholders while keeping enough for business growth.
A13: 12 | B13: R&D Ratio | C13: Research and Development Expense / Net Sales | D13: N/A | E13: N/A | F13: N/A | G13: N/A | H13: N/A | I13: N/A | K13: Not available for all years means Titan spends very little or doesn’t separately report R&D costs, which is common in jewellery and lifestyle sectors.

Sheet KEY PERFORMANCE INDICATORS
A1: OPERATING LEVERAGE = CONTRIBUTION/EBIT
A2: PARTICULARS | B2: 43891 | C2: 44256 | D2: 44621 | E2: 44986 | F2: 45352 | G2: 45717
A3: SALES | B3: ='PROFIT & LOSS'!C2 -> 20010 | C3: ='PROFIT & LOSS'!D2 -> 20602 | D3: ='PROFIT & LOSS'!E2 -> 27210 | E3: ='PROFIT & LOSS'!F2 -> 38270 | F3: ='PROFIT & LOSS'!G2 -> 47114 | G3: ='PROFIT & LOSS'!H2 -> 54842
A4: VARIABLE COST | B4: =('PROFIT & LOSS'!C2*'PROFIT & LOSS'!C5)+('PROFIT & LOSS'!C2*'PROFIT & LOSS'!C8)+('PROFIT & LOSS'!C9*'PROFIT & LOSS'!C2) -> 15807.9 | C4: =('PROFIT & LOSS'!D2*'PROFIT & LOSS'!D5)+('PROFIT & LOSS'!D2*'PROFIT & LOSS'!D8)+('PROFIT & LOSS'!D9*'PROFIT & LOSS'!D2) -> 16893.64 | D4: =('PROFIT & LOSS'!E2*'PROFIT & LOSS'!E5)+('PROFIT & LOSS'!E2*'PROFIT & LOSS'!E8)+('PROFIT & LOSS'!E9*'PROFIT & LOSS'!E2) -> 22040.1 | E4: =('PROFIT & LOSS'!F2*'PROFIT & LOSS'!F5)+('PROFIT & LOSS'!F2*'PROFIT & LOSS'!F8)+('PROFIT & LOSS'!F9*'PROFIT & LOSS'!F2) -> 30998.7 | F4: =('PROFIT & LOSS'!G2*'PROFIT & LOSS'!G5)+('PROFIT & LOSS'!G2*'PROFIT & LOSS'!G8)+('PROFIT & LOSS'!G9*'PROFIT & LOSS'!G2) -> 38633.48 | G4: =('PROFIT & LOSS'!H2*'PROFIT & LOSS'!H5)+('PROFIT & LOSS'!H2*'PROFIT & LOSS'!H8)+('PROFIT & LOSS'!H9*'PROFIT & LOSS'!H2) -> 46067.28
A5: CONTRIBUTION MARGIN | B5: =B3-B4 -> 4202.1 | C5: =C3-C4 -> 3708.36 | D5: =D3-D4 -> 5169.9 | E5: =E3-E4 -> 7271.3 | F5: =F3-F4 -> 8480.52 | G5: =G3-G4 -> 8774.72
A6: EBIT | B6: ='PROFIT & LOSS'!C11-'PROFIT & LOSS'!C17+'PROFIT & LOSS'!C13 -> 2254 | C6: ='PROFIT & LOSS'!D11-'PROFIT & LOSS'!D17+'PROFIT & LOSS'!D13 -> 1414 | D6: ='PROFIT & LOSS'!E11-'PROFIT & LOSS'!E17+'PROFIT & LOSS'!E13 -> 3127 | E6: ='PROFIT & LOSS'!F11-'PROFIT & LOSS'!F17+'PROFIT & LOSS'!F13 -> 4705 | F6: ='PROFIT & LOSS'!G11-'PROFIT & LOSS'!G17+'PROFIT & LOSS'!G13 -> 5087 | G6: ='PROFIT & LOSS'!H11-'PROFIT & LOSS'!H17+'PROFIT & LOSS'!H13 -> 5248
A7: OPERATING LEVERAGE | B7: =B5/B6 -> 1.8642857 | C7: =C5/C6 -> 2.6226025 | D7: =D5/D6 -> 1.6533099 | E7: =E5/E6 -> 1.545441 | F7: =F5/F6 -> 1.6670965 | G7: =G5/G6 -> 1.6720122
A8: INTERPRETATION FOR 2025: 1% change in Sales leads to 1.67% in Profitability.
A10: FINANCIAL LEVERAGE = EBIT/EBT
A11: PARTICULARS | B11: 43891 | C11: 44256 | D11: 44621 | E11: 44986 | F11: 45352 | G11: 45717
A12: EBT | B12: ='PROFIT & LOSS'!C18 -> 2105 | C12: ='PROFIT & LOSS'!D18 -> 1233 | D12: ='PROFIT & LOSS'!E18 -> 2932 | E12: ='PROFIT & LOSS'!F18 -> 4465 | F12: ='PROFIT & LOSS'!G18 -> 4607 | G12: ='PROFIT & LOSS'!H18 -> 4481
A13: EBIT | B13: ='PROFIT & LOSS'!C11-'PROFIT & LOSS'!C17+'PROFIT & LOSS'!C13 -> 2254 | C13: ='PROFIT & LOSS'!D11-'PROFIT & LOSS'!D17+'PROFIT & LOSS'!D13 -> 1414 | D13: ='PROFIT & LOSS'!E11-'PROFIT & LOSS'!E17+'PROFIT & LOSS'!E13 -> 3127 | E13: ='PROFIT & LOSS'!F11-'PROFIT & LOSS'!F17+'PROFIT & LOSS'!F13 -> 4705 | F13: ='PROFIT & LOSS'!G11-'PROFIT & LOSS'!G17+'PROFIT & LOSS'!G13 -> 5087 | G13: ='PROFIT & LOSS'!H11-'PROFIT & LOSS'!H17+'PROFIT & LOSS'!H13 -> 5248
A14: FINANCING LEVERAGE | B14: =B13/B12 -> 1.0707838 | C14: =C13/C12 -> 1.1467964 | D14: =D13/D12 -> 1.0665075 | E14: =E13/E12 -> 1.0537514 | F14: =F13/F12 -> 1.1041893 | G14: =G13/G12 -> 1.1711672
A15: INTERPRETATION FOR 2025: 1% change in EBIT leads to 1.17% in Earning per Share.
A17: TOTAL LEVERAGE = DOL*DFL or CONTRIBUTION/EBT
A18: PARTICULARS | B18: 43891 | C18: 44256 | D18: 44621 | E18: 44986 | F18: 45352 | G18: 45717
A19: FINANCING LEVERAGE | B19: =B13/B12 -> 1.0707838 | C19: =C13/C12 -> 1.1467964 | D19: =D13/D12 -> 1.0665075 | E19: =E13/E12 -> 1.0537514 | F19: =F13/F12 -> 1.1041893 | G19: =G13/G12 -> 1.1711672
A20: =A7 -> OPERATING LEVERAGE | B20: =B7 -> 1.8642857 | C20: =C7 -> 2.6226025 | D20: =D7 -> 1.6533099 | E20: =E7 -> 1.545441 | F20: =F7 -> 1.6670965 | G20: =G7 -> 1.6720122
A21: TOTAL LEVERAGE | B21: =B19*B20 -> 1.996247 | C21: =C19*C20 -> 3.0075912 | D21: =D19*D20 -> 1.7632674 | E21: =E19*E20 -> 1.6285106 | F21: =F19*F20 -> 1.8407901 | G21: =G19*G20 -> 1.9582058
A22: INTERPRETATION FOR 2025: 1% change in Sales leads to 1.95% in Earning per Share.
A24: EBITDA MARGIN = EBITDA/TOTAL SALES*100
A25: PARTICULARS | B25: 43891 | C25: 44256 | D25: 44621 | E25: 44986 | F25: 45352 | G25: 45717 | H25: SPARKLINES
A26: EBITDA | B26: ='PROFIT & LOSS'!B11-'PROFIT & LOSS'!B14-'PROFIT & LOSS'!B15 -> 1902 | C26: ='PROFIT & LOSS'!C11-'PROFIT & LOSS'!C14-'PROFIT & LOSS'!C15 -> 2272 | D26: ='PROFIT & LOSS'!D11-'PROFIT & LOSS'!D14-'PROFIT & LOSS'!D15 -> 1667 | E26: ='PROFIT & LOSS'!E11-'PROFIT & LOSS'!E14-'PROFIT & LOSS'!E15 -> 3090 | F26: ='PROFIT & LOSS'!F11-'PROFIT & LOSS'!F14-'PROFIT & LOSS'!F15 -> 4477 | G26: ='PROFIT & LOSS'!G11-'PROFIT & LOSS'!G14-'PROFIT & LOSS'!G15 -> 4514
A27: TOTAL SALES | B27: ='PROFIT & LOSS'!C2 -> 20010 | C27: ='PROFIT & LOSS'!D2 -> 20602 | D27: ='PROFIT & LOSS'!E2 -> 27210 | E27: ='PROFIT & LOSS'!F2 -> 38270 | F27: ='PROFIT & LOSS'!G2 -> 47114 | G27: ='PROFIT & LOSS'!H2 -> 54842
A28: EBITDA MARGIN | B28: =(B26/B27)*100 -> 9.5052474 | C28: =(C26/C27)*100 -> 11.028056 | D28: =(D26/D27)*100 -> 6.1264241 | E28: =(E26/E27)*100 -> 8.0742096 | F28: =(F26/F27)*100 -> 9.5024833 | G28: =(G26/G27)*100 -> 8.2309179
A29: Titan’s EBITDA margin shows that the company’s operating efficiency dipped in FY22 but recovered steadily to around 8–9% by FY25, indicating strong cost control and stable profitability.
A32: FREE CASH FLOW = CASH FLOW FROM OPERATING ACTIVITIES - CAPITAL EXPENDITURE
A33: PARTICULARS | B33: 43891 | C33: 44256 | D33: 44621 | E33: 44986 | F33: 45352 | G33: 45717 | H33: SPARKLINES
A34: CASH FLOW FROM OPERATING ACTIVITIES | B34: ='CASH FLOW STATEMENT'!C2 -> -289 | C34: ='CASH FLOW STATEMENT'!D2 -> 4101 | D34: ='CASH FLOW STATEMENT'!E2 -> -1126 | E34: ='CASH FLOW STATEMENT'!F2 -> 1810 | F34: ='CASH FLOW STATEMENT'!G2 -> 2030 | G34: ='CASH FLOW STATEMENT'!H2 -> -170
A35: CAPITAL EXPENDITURE | B35: ='CASH FLOW STATEMENT'!B13 -> -226 | C35: ='CASH FLOW STATEMENT'!C13 -> -310 | D35: ='CASH FLOW STATEMENT'!D13 -> -111 | E35: ='CASH FLOW STATEMENT'!E13 -> -173 | F35: ='CASH FLOW STATEMENT'!F13 -> -288 | G35: ='CASH FLOW STATEMENT'!G13 -> -529
A36: FREE CASH FLOW | B36: =B34-B35 -> -63 | C36: =C34-C35 -> 4411 | D36: =D34-D35 -> -1015 | E36: =E34-E35 -> 1983 | F36: =F34-F35 -> 2318 | G36: =G34-G35 -> 359
A37: INTERPRETATION FOR 2025: The company has 359 crores cash that can pay dividends, repay debts or reinvest.
A39: WORKING CAPITAL = CURRENT ASSETS - CURRENT LIABILITIES
A40: PARTICULARS | B40: 43891 | C40: 44256 | D40: 44621 | E40: 44986 | F40: 45352 | G40: 45717 | H40: SPARKLINES
A41: CURRENT ASSETS | B41: ='BALANCE SHEET'!C36 -> 10215.41 | C41: ='BALANCE SHEET'!D36 -> 10443.84 | D41: ='BALANCE SHEET'!E36 -> 17384.87 | E41: ='BALANCE SHEET'!F36 -> 19690.52 | F41: ='BALANCE SHEET'!G36 -> 22439.74 | G41: ='BALANCE SHEET'!H36 -> 30484.17
A42: CURRENT LIABILITIES | B42: ='BALANCE SHEET'!C13 -> 3094 | C42: ='BALANCE SHEET'!D13 -> 3064 | D42: ='BALANCE SHEET'!E13 -> 4159 | E42: ='BALANCE SHEET'!F13 -> 5232 | F42: ='BALANCE SHEET'!G13 -> 5744 | G42: ='BALANCE SHEET'!H13 -> 7093
A43: WORKING CAPITAL | B43: =B41-B42 -> 7121.41 | C43: =C41-C42 -> 7379.84 | D43: =D41-D42 -> 13225.87 | E43: =E41-E42 -> 14458.52 | F43: =F41-F42 -> 16695.74 | G43: =G41-G42 -> 23391.17
A44: INTERPRETATION FOR 2025: The company has a working capital of 23391 Cr. to meet its short term obligations.
A46: LIQUID CAPITAL = (CASH EQUIVALENTS + MARKET SECURITIES + ACCOUNTS RECEIVABLES)-(CURRENT LIABILITIES + LONG TERM DEBT)
A47: PARTICULARS | B47: 43891 | C47: 44256 | D47: 44621 | E47: 44986 | F47: 45352 | G47: 45717 | H47: SPARKLINES
A48: CASH EQUIVALENTS + MARKET SECURITIES + ACCOUNTS RECEIVABLES | B48: ='BALANCE SHEET'!C33+'BALANCE SHEET'!C32 -> 570 | C48: ='BALANCE SHEET'!D33+'BALANCE SHEET'!D32 -> 803 | D48: ='BALANCE SHEET'!E33+'BALANCE SHEET'!E32 -> 1544 | E48: ='BALANCE SHEET'!F33+'BALANCE SHEET'!F32 -> 1700 | F48: ='BALANCE SHEET'!G33+'BALANCE SHEET'!G32 -> 1742 | G48: ='BALANCE SHEET'!H33+'BALANCE SHEET'!H32 -> 2116
A49: CURRENT LIABILITIES + LONG TERM DEBT | B49: ='BALANCE SHEET'!C13+'BALANCE SHEET'!C6 -> 3094 | C49: ='BALANCE SHEET'!D13+'BALANCE SHEET'!D6 -> 3064 | D49: ='BALANCE SHEET'!E13+'BALANCE SHEET'!E6 -> 4159 | E49: ='BALANCE SHEET'!F13+'BALANCE SHEET'!F6 -> 5232 | F49: ='BALANCE SHEET'!G13+'BALANCE SHEET'!G6 -> 8883 | G49: ='BALANCE SHEET'!H13+'BALANCE SHEET'!H6 -> 7513
A50: LIQUID CAPITAL | B50: =B48-B49 -> -2524 | C50: =C48-C49 -> -2261 | D50: =D48-D49 -> -2615 | E50: =E48-E49 -> -3532 | F50: =F48-F49 -> -7141 | G50: =G48-G49 -> -5397
A51: Titan’s liquid capital remained negative throughout FY20–FY25, showing that the company’s readily available assets were not enough to cover its total liabilities, indicating higher dependence on long-term funding or borrowings for its operations.
A54: NOPAT = EBIT*(1-TAX RATE)
A55: PARTICULARS | B55: 43891 | C55: 44256 | D55: 44621 | E55: 44986 | F55: 45352 | G55: 45717 | H55: SPARKLINES
A56: EBIT | B56: =B6 -> 2254 | C56: =C6 -> 1414 | D56: =D6 -> 3127 | E56: =E6 -> 4705 | F56: =F6 -> 5087 | G56: =G6 -> 5248
A57: TAX RATE | B57: ='PROFIT & LOSS'!C19 -> 0.28 | C57: ='PROFIT & LOSS'!D19 -> 0.29 | D57: ='PROFIT & LOSS'!E19 -> 0.26 | E57: ='PROFIT & LOSS'!F19 -> 0.25 | F57: ='PROFIT & LOSS'!G19 -> 0.23 | G57: ='PROFIT & LOSS'!H19 -> 0.26
A58: NOPAT | B58: =B56*(1-B57) -> 1622.88 | C58: =C56*(1-C57) -> 1003.94 | D58: =D56*(1-D57) -> 2313.98 | E58: =E56*(1-E57) -> 3528.75 | F58: =F56*(1-F57) -> 3916.99 | G58: =G56*(1-G57) -> 3883.52
A59: Titan’s NOPAT increased from Rs.1,623 crore in FY20 to Rs.3,884 crore in FY25, showing that the company’s core operating profits after tax have strengthened, indicating improved efficiency in core business operations over the years.
A62: NET INTEREST EXPENSE AFTER TAX = INTEREST EXPENSE*(1-TAX RATE)
A63: PARTICULARS | B63: 43891 | C63: 44256 | D63: 44621 | E63: 44986 | F63: 45352 | G63: 45717 | H63: SPARKLINES
A64: INTEREST EXPENSE | B64: ='PROFIT & LOSS'!C16 -> 149 | C64: ='PROFIT & LOSS'!D16 -> 181 | D64: ='PROFIT & LOSS'!E16 -> 195 | E64: ='PROFIT & LOSS'!F16 -> 240 | F64: ='PROFIT & LOSS'!G16 -> 480 | G64: ='PROFIT & LOSS'!H16 -> 767
A65: TAX RATE | B65: ='PROFIT & LOSS'!C19 -> 0.28 | C65: ='PROFIT & LOSS'!D19 -> 0.29 | D65: ='PROFIT & LOSS'!E19 -> 0.26 | E65: ='PROFIT & LOSS'!F19 -> 0.25 | F65: ='PROFIT & LOSS'!G19 -> 0.23 | G65: ='PROFIT & LOSS'!H19 -> 0.26
A66: NET INTERETS EXPENSE AFTER TAX | B66: =B64*(1-B65) -> 107.28 | C66: =C64*(1-C65) -> 128.51 | D66: =D64*(1-D65) -> 144.3 | E66: =E64*(1-E65) -> 180 | F66: =F64*(1-F65) -> 369.6 | G66: =G64*(1-G65) -> 567.58
A67: Titan’s net interest expense after tax increased from Rs.107 crore in FY20 to Rs.568 crore in FY25, showing that even after accounting for tax benefits, the true cost of debt has risen, indicating higher interest obligations over the years.
A70: INTEREST BEARING LIABILITIES = LONG TERM BORROWINGS+SHORT TERM BORROWING+LEASE LIABILITIES+OTHER BORROWINGS
A71: PARTICULARS | B71: 43891 | C71: 44256 | D71: 44621 | E71: 44986 | F71: 45352 | G71: 45717 | H71: SPARKLINES
A72: LONG TERM BORROWINGS | B72: ='BALANCE SHEET'!C6 -> 0 | C72: ='BALANCE SHEET'!D6 -> 0 | D72: ='BALANCE SHEET'!E6 -> 0 | E72: ='BALANCE SHEET'!F6 -> 0 | F72: ='BALANCE SHEET'!G6 -> 3139 | G72: ='BALANCE SHEET'!H6 -> 420
A73: SHORT TERM BORROWINGS | B73: ='BALANCE SHEET'!C7 -> 2133 | C73: ='BALANCE SHEET'!D7 -> 4094 | D73: ='BALANCE SHEET'!E7 -> 5386 | E73: ='BALANCE SHEET'!F7 -> 6280 | F73: ='BALANCE SHEET'!G7 -> 7608 | G73: ='BALANCE SHEET'!H7 -> 14526
A74: LEASE LIABILITIES | B74: ='BALANCE SHEET'!C8 -> 1136 | C74: ='BALANCE SHEET'!D8 -> 1149 | D74: ='BALANCE SHEET'!E8 -> 1219 | E74: ='BALANCE SHEET'!F8 -> 1582 | F74: ='BALANCE SHEET'!G8 -> 1914 | G74: ='BALANCE SHEET'!H8 -> 2225
A75: OTHER BORROWINGS | B75: 0 | C75: 0 | D75: 0 | E75: 0 | F75: 0 | G75: 0
A76: INTEREST BEARING LIABILITIES | B76: =B72+B73+B74+B75 -> 3269 | C76: =C72+C73+C74+C75 -> 5243 | D76: =D72+D73+D74+D75 -> 6605 | E76: =E72+E73+E74+E75 -> 7862 | F76: =F72+F73+F74+F75 -> 12661 | G76: =G72+G73+G74+G75 -> 17171
A77: Titan’s interest-bearing liabilities increased sharply from Rs.3,269 crore in FY20 to Rs.17,171 crore in FY25, indicating a significant rise in total debt obligations that require interest payments, reflecting greater reliance on borrowed funds for business expansion.
A80: NET LONG TERM ASSETS = GROSS FIXED ASSETS- ACCUMULATED ASSETS
A81: PARTICULARS | B81: 43891 | C81: 44256 | D81: 44621 | E81: 44986 | F81: 45352 | G81: 45717 | H81: SPARKLINES
A82: GROSS FIXED ASSETS | B82: ='BALANCE SHEET'!C25 -> 2634 | C82: ='BALANCE SHEET'!D25 -> 2813 | D82: ='BALANCE SHEET'!E25 -> 3063 | E82: ='BALANCE SHEET'!F25 -> 3587 | F82: ='BALANCE SHEET'!G25 -> 4409 | G82: ='BALANCE SHEET'!H25 -> 5138
A83: ACCUMUKATED DEPRECIATION | B83: ='BALANCE SHEET'!C26 -> 581 | C83: ='BALANCE SHEET'!D26 -> 854 | D83: ='BALANCE SHEET'!E26 -> 1138 | E83: ='BALANCE SHEET'!F26 -> 1426 | F83: ='BALANCE SHEET'!G26 -> 1718 | G83: ='BALANCE SHEET'!H26 -> 2119
A84: NET LONG TERM ASSETS | B84: =B82-B83 -> 2053 | C84: =C82-C83 -> 1959 | D84: =D82-D83 -> 1925 | E84: =E82-E83 -> 2161 | F84: =F82-F83 -> 2691 | G84: =G82-G83 -> 3019
A85: Titan’s net long-term assets increased from Rs.2,053 crore in FY20 to Rs.3,019 crore in FY25, indicating continuous investment in fixed assets and reflecting the company’s growing capital base in property, plant, and equipment.
A88: NET DEBT = TOTAL DEBT - CASH
A89: PARTICULARS | B89: 43891 | C89: 44256 | D89: 44621 | E89: 44986 | F89: 45352 | G89: 45717 | H89: SPARKLINES
A90: TOTAL DEBT | B90: ='BALANCE SHEET'!C5+'BALANCE SHEET'!C9 -> 6363 | C90: ='BALANCE SHEET'!D5+'BALANCE SHEET'!D9 -> 8307 | D90: ='BALANCE SHEET'!E5+'BALANCE SHEET'!E9 -> 10764 | E90: ='BALANCE SHEET'!F5+'BALANCE SHEET'!F9 -> 13094 | F90: ='BALANCE SHEET'!G5+'BALANCE SHEET'!G9 -> 18405 | G90: ='BALANCE SHEET'!H5+'BALANCE SHEET'!H9 -> 24264
A91: CASH | B91: ='BALANCE SHEET'!C33 -> 356 | C91: ='BALANCE SHEET'!D33 -> 512 | D91: ='BALANCE SHEET'!E33 -> 1049 | E91: ='BALANCE SHEET'!F33 -> 792 | F91: ='BALANCE SHEET'!G33 -> 805 | G91: ='BALANCE SHEET'!H33 -> 1132
A92: NET DEBT = TOTAL DEBT - CASH | B92: =B90-B91 -> 6007 | C92: =C90-C91 -> 7795 | D92: =D90-D91 -> 9715 | E92: =E90-E91 -> 12302 | F92: =F90-F91 -> 17600 | G92: =G90-G91 -> 23132
A93: Titan’s net debt rose sharply from Rs.6,007 crore in FY20 to Rs.23,132 crore in FY25, indicating increased leverage and reduced ability to cover debt with available cash, reflecting higher financial dependency on borrowings.
A96: NET ASSETS = TOTAL ASSETS -TOTAL LIABILTIES
A97: PARTICULARS | B97: 43891 | C97: 44256 | D97: 44621 | E97: 44986 | F97: 45352 | G97: 45717 | H97: SPARKLINES
A98: TOTAL ASSETS | B98: ='BALANCE SHEET'!C37 -> 13188 | C98: ='BALANCE SHEET'!D37 -> 15860 | D98: ='BALANCE SHEET'!E37 -> 20137 | E98: ='BALANCE SHEET'!F37 -> 25088 | F98: ='BALANCE SHEET'!G37 -> 32862 | G98: ='BALANCE SHEET'!H37 -> 41075
A99: TOTAL LIABILITIES | B99: ='BALANCE SHEET'!C5+'BALANCE SHEET'!C9 -> 6363 | C99: ='BALANCE SHEET'!D5+'BALANCE SHEET'!D9 -> 8307 | D99: ='BALANCE SHEET'!E5+'BALANCE SHEET'!E9 -> 10764 | E99: ='BALANCE SHEET'!F5+'BALANCE SHEET'!F9 -> 13094 | F99: ='BALANCE SHEET'!G5+'BALANCE SHEET'!G9 -> 18405 | G99: ='BALANCE SHEET'!H5+'BALANCE SHEET'!H9 -> 24264
A100: NET ASSETS | B100: =B98-B99 -> 6825 | C100: =C98-C99 -> 7553 | D100: =D98-D99 -> 9373 | E100: =E98-E99 -> 11994 | F100: =F98-F99 -> 14457 | G100: =G98-G99 -> 16811
A101: Titan’s net assets grew from Rs.6,825 crore in FY20 to Rs.16,811 crore in FY25, indicating strong financial stability and showing that the value remaining for shareholders after paying all liabilities has steadily increased.
A104: NET CAPITAL = EQUITY CAPITAL + RESERVES
A105: PARTICULARS | B105: 43891 | C105: 44256 | D105: 44621 | E105: 44986 | F105: 45352 | G105: 45717 | H105: SPARKLINES
A106: EQUITY CAPITAL | B106: ='BALANCE SHEET'!C2 -> 89 | C106: ='BALANCE SHEET'!D2 -> 89 | D106: ='BALANCE SHEET'!E2 -> 89 | E106: ='BALANCE SHEET'!F2 -> 89 | F106: ='BALANCE SHEET'!G2 -> 89 | G106: ='BALANCE SHEET'!H2 -> 89
A107: RESERVES | B107: ='BALANCE SHEET'!C3 -> 6736 | C107: ='BALANCE SHEET'!D3 -> 7464 | D107: ='BALANCE SHEET'!E3 -> 9284 | E107: ='BALANCE SHEET'!F3 -> 11905 | F107: ='BALANCE SHEET'!G3 -> 14368 | G107: ='BALANCE SHEET'!H3 -> 16722
A108: NET CAPITAL | B108: ='BALANCE SHEET'!C4 -> 6825 | C108: ='BALANCE SHEET'!D4 -> 7553 | D108: ='BALANCE SHEET'!E4 -> 9373 | E108: ='BALANCE SHEET'!F4 -> 11994 | F108: ='BALANCE SHEET'!G4 -> 14457 | G108: ='BALANCE SHEET'!H4 -> 16811
A109: Titan’s net capital rose from Rs.6,825 crore in FY20 to Rs.16,811 crore in FY25, showing a strong buildup of financial resources that can support the company’s long-term growth, expansion, and dividend payments.
A112: OPERATING WORKING CAPITAL = SALES - WORKING CAPITAL
A113: PARTICULARS | B113: 43891 | C113: 44256 | D113: 44621 | E113: 44986 | F113: 45352 | G113: 45717 | H113: SPARKLINES
A114: SALES | B114: ='PROFIT & LOSS'!C2 -> 20010 | C114: ='PROFIT & LOSS'!D2 -> 20602 | D114: ='PROFIT & LOSS'!E2 -> 27210 | E114: ='PROFIT & LOSS'!F2 -> 38270 | F114: ='PROFIT & LOSS'!G2 -> 47114 | G114: ='PROFIT & LOSS'!H2 -> 54842
A115: WORKING CAPITAL | B115: ='BALANCE SHEET'!C36-'BALANCE SHEET'!C13 -> 7121.41 | C115: ='BALANCE SHEET'!D36-'BALANCE SHEET'!D13 -> 7379.84 | D115: ='BALANCE SHEET'!E36-'BALANCE SHEET'!E13 -> 13225.87 | E115: ='BALANCE SHEET'!F36-'BALANCE SHEET'!F13 -> 14458.52 | F115: ='BALANCE SHEET'!G36-'BALANCE SHEET'!G13 -> 16695.74 | G115: ='BALANCE SHEET'!H36-'BALANCE SHEET'!H13 -> 23391.17
A116: OPERATING WORKING CAPITAL | B116: =B114-B115 -> 12888.59 | C116: =C114-C115 -> 13222.16 | D116: =D114-D115 -> 13984.13 | E116: =E114-E115 -> 23811.48 | F116: =F114-F115 -> 30418.26 | G116: =G114-G115 -> 31450.83
A117: Titan’s operating working capital increased from Rs.12,889 crore in FY20 to Rs.31,451 crore in FY25, indicating that the company is using more short-term resources to support daily operations, reflecting business expansion and higher operational activity.
A120: OPERATING WORKING CAPITAL TURNOVER = SALES/WORKING CAPITAL
A121: PARTICULARS | B121: 43891 | C121: 44256 | D121: 44621 | E121: 44986 | F121: 45352 | G121: 45717 | H121: SPARKLINES
A122: SALES | B122: ='PROFIT & LOSS'!C2 -> 20010 | C122: ='PROFIT & LOSS'!D2 -> 20602 | D122: ='PROFIT & LOSS'!E2 -> 27210 | E122: ='PROFIT & LOSS'!F2 -> 38270 | F122: ='PROFIT & LOSS'!G2 -> 47114 | G122: ='PROFIT & LOSS'!H2 -> 54842
A123: WORKING CAPITAL | B123: ='BALANCE SHEET'!C36-'BALANCE SHEET'!C13 -> 7121.41 | C123: ='BALANCE SHEET'!D36-'BALANCE SHEET'!D13 -> 7379.84 | D123: ='BALANCE SHEET'!E36-'BALANCE SHEET'!E13 -> 13225.87 | E123: ='BALANCE SHEET'!F36-'BALANCE SHEET'!F13 -> 14458.52 | F123: ='BALANCE SHEET'!G36-'BALANCE SHEET'!G13 -> 16695.74 | G123: ='BALANCE SHEET'!H36-'BALANCE SHEET'!H13 -> 23391.17
A124: OPERATING WORKING CAPITAL TURNOVER | B124: =B122/B123 -> 2.8098368 | C124: =C122/C123 -> 2.7916594 | D124: =D122/D123 -> 2.0573316 | E124: =E122/E123 -> 2.6468823 | F124: =F122/F123 -> 2.8219174 | G124: =G122/G123 -> 2.3445599
A125: Titan’s operating working capital turnover fluctuated between 2.05 and 2.82 times, showing the company’s moderate efficiency in using working capital to generate sales, with stable but slightly declining utilization in recent years.
...

Sheet PROJECT FINANCING
B2: FCFF CALCULATION | C2: NOPAT+DEP AND AMOR - CAPEX -NET CHANGE IN WORKING CAPITAL
B4: PARTICULARS | C4: FORMULA | D4: 2020 | E4: 2021 | F4: 2022 | G4: 2023 | H4: 2024 | I4: 2025 | J4: 2026 | K4: 2027 | L4: 2028
B5: EBIT CALCULATIONS | C5: PBT+INTEREST
B6: Profit before tax | D6: ='PROFIT & LOSS'!C18 -> 2105 | E6: ='PROFIT & LOSS'!D18 -> 1233 | F6: ='PROFIT & LOSS'!E18 -> 2932 | G6: ='PROFIT & LOSS'!F18 -> 4465 | H6: ='PROFIT & LOSS'!G18 -> 4607 | I6: ='PROFIT & LOSS'!H18 -> 4481
B7: Interest | D7: ='PROFIT & LOSS'!C16 -> 149 | E7: ='PROFIT & LOSS'!D16 -> 181 | F7: ='PROFIT & LOSS'!E16 -> 195 | G7: ='PROFIT & LOSS'!F16 -> 240 | H7: ='PROFIT & LOSS'!G16 -> 480 | I7: ='PROFIT & LOSS'!H16 -> 767
B8: EBIT | D8: =SUM(D6:D7) -> 2254 | E8: =SUM(E6:E7) -> 1414 | F8: =SUM(F6:F7) -> 3127 | G8: =SUM(G6:G7) -> 4705 | H8: =SUM(H6:H7) -> 5087 | I8: =SUM(I6:I7) -> 5248
B9: Tax % | D9: ='PROFIT & LOSS'!C19 -> 0.28 | E9: ='PROFIT & LOSS'!D19 -> 0.29 | F9: ='PROFIT & LOSS'!E19 -> 0.26 | G9: ='PROFIT & LOSS'!F19 -> 0.25 | H9: ='PROFIT & LOSS'!G19 -> 0.23 | I9: ='PROFIT & LOSS'!H19 -> 0.26
B10: NOPAT EBIT(1-TAX) | D10: =D8*(1-D9) -> 1622.88 | E10: =E8*(1-E9) -> 1003.94 | F10: =F8*(1-F9) -> 2313.98 | G10: =G8*(1-G9) -> 3528.75 | H10: =H8*(1-H9) -> 3916.99 | I10: =I8*(1-I9) -> 3883.52
B11: Depreciation | D11: ='PROFIT & LOSS'!C17 -> 310 | E11: ='PROFIT & LOSS'!D17 -> 331 | F11: ='PROFIT & LOSS'!E17 -> 347 | G11: ='PROFIT & LOSS'!F17 -> 364 | H11: ='PROFIT & LOSS'!G17 -> 447 | I11: ='PROFIT & LOSS'!H17 -> 537
B12: WORKING CAPITAL CALCULATION | C12: CURRENT ASSET - CURRENT LIABILITY
B13: CURRENT ASSET | D13: ='BALANCE SHEET'!C36 -> 10215.41 | E13: ='BALANCE SHEET'!D36 -> 10443.84 | F13: ='BALANCE SHEET'!E36 -> 17384.87 | G13: ='BALANCE SHEET'!F36 -> 19690.52 | H13: ='BALANCE SHEET'!G36 -> 22439.74 | I13: ='BALANCE SHEET'!H36 -> 30484.17
B14: CURRENT LAIBILITIES | D14: ='BALANCE SHEET'!C13 -> 3094 | E14: ='BALANCE SHEET'!D13 -> 3064 | F14: ='BALANCE SHEET'!E13 -> 4159 | G14: ='BALANCE SHEET'!F13 -> 5232 | H14: ='BALANCE SHEET'!G13 -> 5744 | I14: ='BALANCE SHEET'!H13 -> 7093
B15: WORKING CAPITAL | D15: =D13-D14 -> 7121.41 | E15: =E13-E14 -> 7379.84 | F15: =F13-F14 -> 13225.87 | G15: =G13-G14 -> 14458.52 | H15: =H13-H14 -> 16695.74 | I15: =I13-I14 -> 23391.17
B16: CHANGE IN WORKING CAPITAL CALCULATION | C16: CURRENT WORKING CAPITAL - PREVIOUS WORKING CAPITAL
B17: CHANGE IN WORKING CAPITAL | D17: ='PROJECT FINANCING'!D15-('BALANCE SHEET'!B36-'BALANCE SHEET'!B13) -> 556.22 | E17: =E15-D15 -> 258.43 | F17: =F15-E15 -> 5846.03 | G17: =G15-F15 -> 1232.65 | H17: =H15-G15 -> 2237.22 | I17: =I15-H15 -> 6695.43
B18: CAPEX CALCULATION | C18: NET CHANGE IN FIXED ASSET +DEP
B19: FIXED ASSET | D19: ='BALANCE SHEET'!C15 -> 2053 | E19: ='BALANCE SHEET'!D15 -> 1959 | F19: ='BALANCE SHEET'!E15 -> 1925 | G19: ='BALANCE SHEET'!F15 -> 2161 | H19: ='BALANCE SHEET'!G15 -> 2691 | I19: ='BALANCE SHEET'!H15 -> 3019
B20: change in fixed asset | D20: =D19-'BALANCE SHEET'!B15 -> 984 | E20: =E19-D19 -> -94 | F20: =F19-E19 -> -34 | G20: =G19-F19 -> 236 | H20: =H19-G19 -> 530 | I20: =I19-H19 -> 328
B21: Depreciation | D21: =D11 -> 310 | E21: =E11 -> 331 | F21: =F11 -> 347 | G21: =G11 -> 364 | H21: =H11 -> 447 | I21: =I11 -> 537
B22: CAPEX | D22: =D20+D21 -> 1294 | E22: =E20+E21 -> 237 | F22: =F20+F21 -> 313 | G22: =G20+G21 -> 600 | H22: =H20+H21 -> 977 | I22: =I20+I21 -> 865
B23: GROWTH RATE (CAGR) | C23: ASSUMPTION: TAKEN INDUSTRY CAGR AS GROWTH FACTOR | D23: 0.06 | E23: 0.06 | F23: 0.06 | G23: 0.06 | H23: 0.06 | I23: 0.06 | J23: 0.06 | K23: 0.06 | L23: 0.06
B24: FCFF | D24: =D10+D11-D17-D22 -> 82.66 | E24: =E10+E11-E17-E22 -> 839.51 | F24: =F10+F11-F17-F22 -> -3498.05 | G24: =G10+G11-G17-G22 -> 2060.1 | H24: =H10+H11-H17-H22 -> 1149.77 | I24: =I10+I11-I17-I22 -> -3139.91
B25: PROJECTED FCFF | J25: =I24*(1+I23) -> -3328.3046 | K25: =J25*(1+J23) -> -3528.0029 | L25: =K25*(1+K23) -> -3739.683
B26: NPV, IF DISCOUNT RATE IS 10% | D26: =NPV(10%,D24) -> 75.145455 | E26: =NPV(10%,E24) -> 763.19091 | F26: =NPV(10%,F24) -> -3180.0455 | G26: =NPV(10%,G24) -> 1872.8182 | H26: =NPV(10%,H24) -> 1045.2455 | I26: =NPV(10%,I24) -> -2854.4636 | J26: =NPV(10%,J25) -> -3025.7315 | K26: =NPV(10%,K25) -> -3207.2753 | L26: =NPV(10%,L25) -> -3399.7119

Sheet MONTE CARLO SIMULATION
B1: PBT | C1: Interest | D1: EBIT | E1: Tax | F1: NOPAT = EBIT(1-tax) | G1: Depreciation | H1: Working capital Changes | I1: Capex | J1: FCFF | M1: NOPAT | N1: Depreciation | O1: Working Capital Changes | P1: Capex | Q1: FCFF
A2: Average | B2: =AVERAGE('PROFIT & LOSS'!C18:H18) -> 3303.8333 | C2: =AVERAGE('PROFIT & LOSS'!C16:H16) -> 335.33333 | D2: =B2+C2 -> 3639.1667 | E2: =AVERAGE('PROFIT & LOSS'!C19:H19) -> 0.26166667 | F2: =D2*(1-E2) -> 2686.9181 | G2: =AVERAGE('PROFIT & LOSS'!C17:H17) -> 389.33333 | H2: =AVERAGE('PROJECT FINANCING'!D17:I17) -> 2804.33 | I2: =AVERAGE('PROJECT FINANCING'!D22:I22) -> 714.33333 | J2: =AVERAGE('PROJECT FINANCING'!D24:I24) -> -417.65333 | L2: Mean | M2: =AVERAGE(B7:B1005) -> 2744.9004 | N2: =AVERAGE(D7:D1005) -> 394.37722 | O2: =AVERAGE(F7:F1005) -> 2740.8765 | P2: =AVEDEV(H7:H1005) -> 2176.2633 | Q2: =AVERAGE(J7:J1005) -> -615.4881
A3: Standard Deviation | B3: =_xlfn.STDEV.S('PROFIT & LOSS'!C18:H18) -> 1434.9972 | C3: =_xlfn.STDEV.S('PROFIT & LOSS'!C16:H16) -> 242.72838 | D3: =C3+B3 -> 1677.7256 | E3: =_xlfn.STDEV.S('PROFIT & LOSS'!C19:H19) -> 0.021369761 | F3: =D3*(1-E3) -> 1641.873 | G3: =_xlfn.STDEV.S('PROFIT & LOSS'!C17:H17) -> 86.326512 | H3: =_xlfn.STDEV.S('PROJECT FINANCING'!D17:I17) -> 2782.8042 | I3: =_xlfn.STDEV.S('PROJECT FINANCING'!D17:I17) -> 2782.8042 | J3: =_xlfn.STDEV.S('PROJECT FINANCING'!D24:I24) -> 2337.7928 | L3: Maximum | M3: =MAX(B7:B1005) -> 8234.0304 | N3: =MAX(D7:D1005) -> 669.12507 | O3: =MAX(F7:F1005) -> 11694.439 | P3: =MAX(H7:H1005) -> 10282.575 | Q3: =MAX(J7:J1005) -> 6582.705
A4: First Iteration | B4: =_xlfn.NORM.INV(RAND(),B2,B3) -> 1806.8226 | C4: =_xlfn.NORM.INV(RAND(),C2,C3) -> 188.22293 | D4: =_xlfn.NORM.INV(RAND(),D2,D3) -> 3328.2806 | E4: =_xlfn.NORM.INV(RAND(),E2,E3) -> 0.26324381 | F4: =_xlfn.NORM.INV(RAND(),F2,F3) -> 2920.1333 | G4: =_xlfn.NORM.INV(RAND(),G2,G3) -> 373.28926 | H4: =_xlfn.NORM.INV(RAND(),H2,H3) -> 2398.8558 | I4: =_xlfn.NORM.INV(RAND(),I2,I3) -> 1979.2113 | J4: =_xlfn.NORM.INV(RAND(),J2,J3) -> -3434.0951 | L4: Minimum | M4: =MIN(B7:B1005) -> -3143.6513 | N4: =MIN(D989) -> 404.56232 | O4: =MIN(F7:F1005) -> -6360.2237 | P4: =MIN(H7:H1005) -> -8606.5128 | Q4: =MIN(J7:J1005) -> -8768.2858
L5: median | M5: =MEDIAN(B7:B1005) -> 2795.9641 | N5: =MEDIAN(D7:D1005) -> 397.00403 | O5: =MEDIAN(F7:F1005) -> 2659.2115 | P5: =MEDIAN(H7:H1005) -> 802.07184 | Q5: =MEDIAN(J7:J1005) -> -666.61227
A6: Simulation Number | B6: NOPAT | C6: Simulation number | D6: Depreciation | E6: Simulation number | F6: Working Capital Changes | G6: Simulation number | H6: Capex | I6: Simulation number | J6: FCFF | L6: std. D. | M6: {=_xlfn.STDEV.S(B7:B1005)} -> 1613.0371 | N6: =_xlfn.STDEV.S(D7:D1005) -> 85.533881 | O6: =_xlfn.STDEV.S(F7:F1005) -> 2888.4444 | P6: =_xlfn.STDEV.S(H7:H1005) -> 2727.9149 | Q6: {=_xlfn.STDEV.S(J7:J1005)} -> 2376.3473
A7: 1 | B7: =F4 -> 2920.1333 | C7: 1 | D7: =G4 -> 373.28926 | E7: 1 | F7: =H4 -> 2398.8558 | G7: 1 | H7: =I4 -> 1979.2113 | I7: 1 | J7: =J4 -> -3434.0951
A8: 2 | B8: 3080.2334 | C8: 2 | D8: 421.39922 | E8: 2 | F8: 1127.9341 | G8: 2 | H8: 3143.7601 | I8: 2 | J8: -3400.0647
A9: 3 | B9: 4605.4278 | C9: 3 | D9: 312.70963 | E9: 3 | F9: 3732.4985 | G9: 3 | H9: 198.81414 | I9: 3 | J9: -1691.8769
A10: 4 | B10: 2233.9298 | C10: 4 | D10: 382.166 | E10: 4 | F10: 6109.266 | G10: 4 | H10: 4221.6357 | I10: 4 | J10: -3545.207
A11: 5 | B11: 3745.6598 | C11: 5 | D11: 544.86293 | E11: 5 | F11: 1257.4835 | G11: 5 | H11: -1994.3167 | I11: 5 | J11: -3001.25
A12: 6 | B12: 2088.0944 | C12: 6 | D12: 531.27805 | E12: 6 | F12: 2060.214 | G12: 6 | H12: 4294.9009 | I12: 6 | J12: -10.301245
A13: 7 | B13: 4477.6423 | C13: 7 | D13: 454.75891 | E13: 7 | F13: 4038.5047 | G13: 7 | H13: -823.79737 | I13: 7 | J13: 943.28559
A14: 8 | B14: 3106.1913 | C14: 8 | D14: 284.28937 | E14: 8 | F14: 2315.9934 | G14: 8 | H14: -1280.3852 | I14: 8 | J14: 1576.6022
A15: 9 | B15: -7.2649469 | C15: 9 | D15: 413.33142 | E15: 9 | F15: 6449.452 | G15: 9 | H15: 692.81783 | I15: 9 | J15: 5084.2826
A16: 10 | B16: 4245.3496 | C16: 10 | D16: 449.45786 | E16: 10 | F16: 6072.9214 | G16: 10 | H16: -39.244886 | I16: 10 | J16: 3469.9261
A17: 11 | B17: 4244.0953 | C17: 11 | D17: 531.79497 | E17: 11 | F17: 2147.7891 | G17: 11 | H17: -774.0506 | I17: 11 | J17: -1945.2325
A18: 12 | B18: 3023.4727 | C18: 12 | D18: 257.40773 | E18: 12 | F18: 4538.7405 | G18: 12 | H18: 2562.0415 | I18: 12 | J18: 2434.726
A19: 13 | B19: 3722.8656 | C19: 13 | D19: 500.78243 | E19: 13 | F19: 1969.2013 | G19: 13 | H19: -632.071 | I19: 13 | J19: -1097.8658
... A1005: 999 | B1005: 3248.0827 | C1005: 999 | D1005: 507.52544 | E1005: 999 | F1005: 193.44694 | G1005: 999 | H1005: 2357.7472 | I1005: 999 | J1005: -782.44032
